<program> at 1:1.
  <subdef> at 2:1.
    <type> at 2:8.
    </type> at 2:18.
    <type> at 2:24.
    </type> at 2:27.
    <body> at 3:2.
      <vardef> at 3:2.
        <type> at 3:2.
        </type> at 3:6.
      </vardef> at 4:2.
      <statements> at 4:2.
        <statement> at 4:2.
          <assign> at 4:2.
            <expr> at 4:12.
              <simple> at 4:12.
                <term> at 4:12.
                  <factor> at 4:12.
                  </factor> at 4:13.
                </term> at 4:13.
              </simple> at 4:13.
            </expr> at 4:13.
          </assign> at 4:13.
        </statement> at 4:13.
        <statement> at 5:2.
          <while> at 5:2.
            <expr> at 5:8.
              <simple> at 5:8.
                <term> at 5:8.
                  <factor> at 5:8.
                    <expr> at 5:9.
                      <simple> at 5:9.
                        <term> at 5:9.
                          <factor> at 5:9.
                            <index> at 5:10.
                              <simple> at 5:11.
                                <term> at 5:11.
                                  <factor> at 5:11.
                                  </factor> at 5:14.
                                </term> at 5:14.
                              </simple> at 5:14.
                            </index> at 5:16.
                          </factor> at 5:16.
                        </term> at 5:16.
                      </simple> at 5:16.
                      <simple> at 5:19.
                        <term> at 5:19.
                          <factor> at 5:19.
                          </factor> at 5:20.
                        </term> at 5:20.
                      </simple> at 5:20.
                    </expr> at 5:20.
                  </factor> at 5:22.
                </term> at 5:22.
              </simple> at 5:22.
            </expr> at 5:22.
            <statements> at 6:3.
              <statement> at 6:3.
                <assign> at 6:3.
                  <expr> at 6:13.
                    <simple> at 6:13.
                      <term> at 6:13.
                        <factor> at 6:13.
                        </factor> at 6:17.
                      </term> at 6:17.
                      <term> at 6:19.
                        <factor> at 6:19.
                        </factor> at 7:2.
                      </term> at 7:2.
                    </simple> at 7:2.
                  </expr> at 7:2.
                </assign> at 7:2.
              </statement> at 7:2.
            </statements> at 7:2.
          </while> at 7:5.
        </statement> at 7:5.
        <statement> at 8:2.
          <return> at 8:2.
            <expr> at 8:9.
              <simple> at 8:9.
                <term> at 8:9.
                  <factor> at 8:9.
                  </factor> at 10:1.
                </term> at 10:1.
              </simple> at 10:1.
            </expr> at 10:1.
          </return> at 10:1.
        </statement> at 10:1.
      </statements> at 10:1.
    </body> at 10:1.
  </subdef> at 10:1.
  <subdef> at 10:1.
    <type> at 10:6.
    </type> at 10:16.
    <type> at 10:19.
    </type> at 10:29.
    <type> at 10:35.
    </type> at 10:44.
    <body> at 11:2.
      <vardef> at 11:2.
        <type> at 11:2.
        </type> at 11:12.
      </vardef> at 12:2.
      <vardef> at 12:2.
        <type> at 12:2.
        </type> at 12:6.
      </vardef> at 14:2.
      <statements> at 14:2.
        <statement> at 14:2.
          <assign> at 14:2.
            <expr> at 14:14.
              <simple> at 14:14.
                <term> at 14:14.
                  <factor> at 14:14.
                    <arglist> at 14:20.
                      <expr> at 14:21.
                        <simple> at 14:21.
                          <term> at 14:21.
                            <factor> at 14:21.
                            </factor> at 14:22.
                          </term> at 14:22.
                        </simple> at 14:22.
                      </expr> at 14:22.
                    </arglist> at 14:23.
                  </factor> at 14:23.
                </term> at 14:23.
              </simple> at 14:23.
            </expr> at 14:23.
          </assign> at 14:23.
        </statement> at 14:23.
        <statement> at 15:2.
          <assign> at 15:2.
            <expr> at 15:14.
              <simple> at 15:14.
                <term> at 15:14.
                  <factor> at 15:14.
                    <arglist> at 15:20.
                      <expr> at 15:21.
                        <simple> at 15:21.
                          <term> at 15:21.
                            <factor> at 15:21.
                            </factor> at 15:22.
                          </term> at 15:22.
                        </simple> at 15:22.
                      </expr> at 15:22.
                    </arglist> at 15:23.
                  </factor> at 15:23.
                </term> at 15:23.
              </simple> at 15:23.
            </expr> at 15:23.
          </assign> at 15:23.
        </statement> at 15:23.
        <statement> at 16:2.
          <assign> at 16:2.
            <expr> at 16:16.
              <simple> at 16:16.
                <term> at 16:16.
                  <factor> at 16:16.
                  </factor> at 16:22.
                </term> at 16:22.
                <term> at 16:24.
                  <factor> at 16:24.
                  </factor> at 16:29.
                </term> at 16:29.
              </simple> at 16:29.
            </expr> at 16:29.
          </assign> at 16:29.
        </statement> at 16:29.
        <statement> at 17:2.
          <assign> at 17:2.
            <expr> at 17:12.
              <simple> at 17:12.
                <term> at 17:12.
                  <factor> at 17:12.
                  </factor> at 17:13.
                </term> at 17:13.
              </simple> at 17:13.
            </expr> at 17:13.
          </assign> at 17:13.
        </statement> at 17:13.
        <statement> at 18:2.
          <assign> at 18:2.
            <simple> at 18:18.
              <term> at 18:18.
                <factor> at 18:18.
                </factor> at 18:26.
              </term> at 18:26.
              <term> at 18:28.
                <factor> at 18:28.
                </factor> at 18:29.
              </term> at 18:29.
            </simple> at 18:29.
          </assign> at 18:29.
        </statement> at 18:29.
        <statement> at 20:2.
          <while> at 20:2.
            <expr> at 20:8.
              <simple> at 20:8.
                <term> at 20:8.
                  <factor> at 20:8.
                    <expr> at 20:9.
                      <simple> at 20:9.
                        <term> at 20:9.
                          <factor> at 20:9.
                          </factor> at 20:13.
                        </term> at 20:13.
                      </simple> at 20:13.
                      <simple> at 20:15.
                        <term> at 20:15.
                          <factor> at 20:15.
                          </factor> at 20:20.
                        </term> at 20:20.
                      </simple> at 20:20.
                    </expr> at 20:20.
                  </factor> at 20:21.
                </term> at 20:21.
              </simple> at 20:21.
            </expr> at 20:21.
            <statements> at 21:3.
              <statement> at 21:3.
                <assign> at 21:3.
                  <index> at 21:10.
                    <simple> at 21:11.
                      <term> at 21:11.
                        <factor> at 21:11.
                        </factor> at 21:14.
                      </term> at 21:14.
                    </simple> at 21:14.
                  </index> at 21:16.
                  <expr> at 21:18.
                    <simple> at 21:18.
                      <term> at 21:18.
                        <factor> at 21:18.
                          <index> at 21:19.
                            <simple> at 21:20.
                              <term> at 21:20.
                                <factor> at 21:20.
                                </factor> at 21:23.
                              </term> at 21:23.
                            </simple> at 21:23.
                          </index> at 21:24.
                        </factor> at 21:24.
                      </term> at 21:24.
                    </simple> at 21:24.
                  </expr> at 21:24.
                </assign> at 21:24.
              </statement> at 21:24.
              <statement> at 22:3.
                <assign> at 22:3.
                  <expr> at 22:13.
                    <simple> at 22:13.
                      <term> at 22:13.
                        <factor> at 22:13.
                        </factor> at 22:17.
                      </term> at 22:17.
                      <term> at 22:19.
                        <factor> at 22:19.
                        </factor> at 23:2.
                      </term> at 23:2.
                    </simple> at 23:2.
                  </expr> at 23:2.
                </assign> at 23:2.
              </statement> at 23:2.
            </statements> at 23:2.
          </while> at 23:5.
        </statement> at 23:5.
        <statement> at 25:2.
          <while> at 25:2.
            <expr> at 25:8.
              <simple> at 25:8.
                <term> at 25:8.
                  <factor> at 25:8.
                    <expr> at 25:9.
                      <simple> at 25:9.
                        <term> at 25:9.
                          <factor> at 25:9.
                          </factor> at 25:13.
                        </term> at 25:13.
                      </simple> at 25:13.
                      <simple> at 25:15.
                        <term> at 25:15.
                          <factor> at 25:15.
                          </factor> at 25:22.
                        </term> at 25:22.
                      </simple> at 25:22.
                    </expr> at 25:22.
                  </factor> at 25:23.
                </term> at 25:23.
              </simple> at 25:23.
            </expr> at 25:23.
            <statements> at 26:3.
              <statement> at 26:3.
                <assign> at 26:3.
                  <index> at 26:10.
                    <simple> at 26:11.
                      <term> at 26:11.
                        <factor> at 26:11.
                        </factor> at 26:14.
                      </term> at 26:14.
                    </simple> at 26:14.
                  </index> at 26:16.
                  <expr> at 26:18.
                    <simple> at 26:18.
                      <term> at 26:18.
                        <factor> at 26:18.
                          <index> at 26:19.
                            <simple> at 26:20.
                              <term> at 26:20.
                                <factor> at 26:20.
                                </factor> at 26:24.
                              </term> at 26:24.
                              <term> at 26:26.
                                <factor> at 26:26.
                                </factor> at 26:31.
                              </term> at 26:31.
                            </simple> at 26:31.
                          </index> at 26:32.
                        </factor> at 26:32.
                      </term> at 26:32.
                    </simple> at 26:32.
                  </expr> at 26:32.
                </assign> at 26:32.
              </statement> at 26:32.
              <statement> at 27:3.
                <assign> at 27:3.
                  <expr> at 27:13.
                    <simple> at 27:13.
                      <term> at 27:13.
                        <factor> at 27:13.
                        </factor> at 27:17.
                      </term> at 27:17.
                      <term> at 27:19.
                        <factor> at 27:19.
                        </factor> at 28:2.
                      </term> at 28:2.
                    </simple> at 28:2.
                  </expr> at 28:2.
                </assign> at 28:2.
              </statement> at 28:2.
            </statements> at 28:2.
          </while> at 28:5.
        </statement> at 28:5.
        <statement> at 30:2.
          <assign> at 30:2.
            <index> at 30:9.
              <simple> at 30:10.
                <term> at 30:10.
                  <factor> at 30:10.
                  </factor> at 30:13.
                </term> at 30:13.
              </simple> at 30:13.
            </index> at 30:15.
            <expr> at 30:17.
              <simple> at 30:17.
                <term> at 30:17.
                  <factor> at 30:17.
                  </factor> at 30:18.
                </term> at 30:18.
              </simple> at 30:18.
            </expr> at 30:18.
          </assign> at 30:18.
        </statement> at 30:18.
        <statement> at 32:2.
          <return> at 32:2.
            <expr> at 32:9.
              <simple> at 32:9.
                <term> at 32:9.
                  <factor> at 32:9.
                  </factor> at 34:1.
                </term> at 34:1.
              </simple> at 34:1.
            </expr> at 34:1.
          </return> at 34:1.
        </statement> at 34:1.
      </statements> at 34:1.
    </body> at 34:1.
  </subdef> at 34:1.
  <subdef> at 34:1.
    <type> at 34:7.
    </type> at 34:17.
    <body> at 35:2.
      <vardef> at 35:2.
        <type> at 35:2.
        </type> at 35:6.
      </vardef> at 36:2.
      <statements> at 36:2.
        <statement> at 36:2.
          <assign> at 36:2.
            <expr> at 36:10.
              <simple> at 36:10.
                <term> at 36:10.
                  <factor> at 36:10.
                  </factor> at 36:11.
                </term> at 36:11.
              </simple> at 36:11.
            </expr> at 36:11.
          </assign> at 36:11.
        </statement> at 36:11.
        <statement> at 37:2.
          <while> at 37:2.
            <expr> at 37:8.
              <simple> at 37:8.
                <term> at 37:8.
                  <factor> at 37:8.
                    <expr> at 37:9.
                      <simple> at 37:9.
                        <term> at 37:9.
                          <factor> at 37:9.
                            <index> at 37:13.
                              <simple> at 37:14.
                                <term> at 37:14.
                                  <factor> at 37:14.
                                  </factor> at 37:15.
                                </term> at 37:15.
                              </simple> at 37:15.
                            </index> at 37:17.
                          </factor> at 37:17.
                        </term> at 37:17.
                      </simple> at 37:17.
                      <simple> at 37:20.
                        <term> at 37:20.
                          <factor> at 37:20.
                          </factor> at 37:21.
                        </term> at 37:21.
                      </simple> at 37:21.
                    </expr> at 37:21.
                  </factor> at 37:22.
                </term> at 37:22.
              </simple> at 37:22.
            </expr> at 37:22.
            <statements> at 38:3.
              <statement> at 38:3.
                <assign> at 38:3.
                  <expr> at 38:11.
                    <simple> at 38:11.
                      <term> at 38:11.
                        <factor> at 38:11.
                          <index> at 38:15.
                            <simple> at 38:16.
                              <term> at 38:16.
                                <factor> at 38:16.
                                </factor> at 38:17.
                              </term> at 38:17.
                            </simple> at 38:17.
                          </index> at 38:18.
                        </factor> at 38:18.
                      </term> at 38:18.
                    </simple> at 38:18.
                  </expr> at 38:18.
                </assign> at 38:18.
              </statement> at 38:18.
              <statement> at 39:3.
                <if> at 39:3.
                  <expr> at 39:6.
                    <simple> at 39:6.
                      <term> at 39:6.
                        <factor> at 39:6.
                        </factor> at 39:8.
                      </term> at 39:8.
                    </simple> at 39:8.
                    <simple> at 39:10.
                      <term> at 39:10.
                        <factor> at 39:10.
                        </factor> at 39:11.
                      </term> at 39:11.
                    </simple> at 39:11.
                  </expr> at 39:11.
                  <statements> at 39:13.
                    <statement> at 39:13.
                      <output> at 39:13.
                      </output> at 40:3.
                    </statement> at 40:3.
                  </statements> at 40:3.
                  <elif> at 40:3.
                  <expr> at 40:8.
                    <simple> at 40:8.
                      <term> at 40:8.
                        <factor> at 40:8.
                        </factor> at 40:10.
                      </term> at 40:10.
                    </simple> at 40:10.
                    <simple> at 40:12.
                      <term> at 40:12.
                        <factor> at 40:12.
                        </factor> at 40:14.
                      </term> at 40:14.
                    </simple> at 40:14.
                  </expr> at 40:14.
                  <statements> at 40:16.
                    <statement> at 40:16.
                      <output> at 40:16.
                      </output> at 41:3.
                    </statement> at 41:3.
                  </statements> at 41:3.
                  </elif> at 41:3.
                  <elif> at 41:3.
                  <expr> at 41:8.
                    <simple> at 41:8.
                      <term> at 41:8.
                        <factor> at 41:8.
                        </factor> at 41:10.
                      </term> at 41:10.
                    </simple> at 41:10.
                    <simple> at 41:12.
                      <term> at 41:12.
                        <factor> at 41:12.
                        </factor> at 41:14.
                      </term> at 41:14.
                    </simple> at 41:14.
                  </expr> at 41:14.
                  <statements> at 41:16.
                    <statement> at 41:16.
                      <output> at 41:16.
                      </output> at 42:3.
                    </statement> at 42:3.
                  </statements> at 42:3.
                  </elif> at 42:3.
                  <elif> at 42:3.
                  <expr> at 42:8.
                    <simple> at 42:8.
                      <term> at 42:8.
                        <factor> at 42:8.
                        </factor> at 42:10.
                      </term> at 42:10.
                    </simple> at 42:10.
                    <simple> at 42:12.
                      <term> at 42:12.
                        <factor> at 42:12.
                        </factor> at 42:14.
                      </term> at 42:14.
                    </simple> at 42:14.
                  </expr> at 42:14.
                  <statements> at 42:16.
                    <statement> at 42:16.
                      <output> at 42:16.
                      </output> at 43:3.
                    </statement> at 43:3.
                  </statements> at 43:3.
                  </elif> at 43:3.
                  <elif> at 43:3.
                  <expr> at 43:8.
                    <simple> at 43:8.
                      <term> at 43:8.
                        <factor> at 43:8.
                        </factor> at 43:10.
                      </term> at 43:10.
                    </simple> at 43:10.
                    <simple> at 43:12.
                      <term> at 43:12.
                        <factor> at 43:12.
                        </factor> at 43:14.
                      </term> at 43:14.
                    </simple> at 43:14.
                  </expr> at 43:14.
                  <statements> at 43:16.
                    <statement> at 43:16.
                      <output> at 43:16.
                      </output> at 44:3.
                    </statement> at 44:3.
                  </statements> at 44:3.
                  </elif> at 44:3.
                  <elif> at 44:3.
                  <expr> at 44:8.
                    <simple> at 44:8.
                      <term> at 44:8.
                        <factor> at 44:8.
                        </factor> at 44:10.
                      </term> at 44:10.
                    </simple> at 44:10.
                    <simple> at 44:12.
                      <term> at 44:12.
                        <factor> at 44:12.
                        </factor> at 44:14.
                      </term> at 44:14.
                    </simple> at 44:14.
                  </expr> at 44:14.
                  <statements> at 44:16.
                    <statement> at 44:16.
                      <output> at 44:16.
                      </output> at 45:3.
                    </statement> at 45:3.
                  </statements> at 45:3.
                  </elif> at 45:3.
                  <elif> at 45:3.
                  <expr> at 45:8.
                    <simple> at 45:8.
                      <term> at 45:8.
                        <factor> at 45:8.
                        </factor> at 45:10.
                      </term> at 45:10.
                    </simple> at 45:10.
                    <simple> at 45:12.
                      <term> at 45:12.
                        <factor> at 45:12.
                        </factor> at 45:14.
                      </term> at 45:14.
                    </simple> at 45:14.
                  </expr> at 45:14.
                  <statements> at 45:16.
                    <statement> at 45:16.
                      <output> at 45:16.
                      </output> at 46:3.
                    </statement> at 46:3.
                  </statements> at 46:3.
                  </elif> at 46:3.
                  <elif> at 46:3.
                  <expr> at 46:8.
                    <simple> at 46:8.
                      <term> at 46:8.
                        <factor> at 46:8.
                        </factor> at 46:10.
                      </term> at 46:10.
                    </simple> at 46:10.
                    <simple> at 46:12.
                      <term> at 46:12.
                        <factor> at 46:12.
                        </factor> at 46:14.
                      </term> at 46:14.
                    </simple> at 46:14.
                  </expr> at 46:14.
                  <statements> at 46:16.
                    <statement> at 46:16.
                      <output> at 46:16.
                      </output> at 47:3.
                    </statement> at 47:3.
                  </statements> at 47:3.
                  </elif> at 47:3.
                  <elif> at 47:3.
                  <expr> at 47:8.
                    <simple> at 47:8.
                      <term> at 47:8.
                        <factor> at 47:8.
                        </factor> at 47:10.
                      </term> at 47:10.
                    </simple> at 47:10.
                    <simple> at 47:12.
                      <term> at 47:12.
                        <factor> at 47:12.
                        </factor> at 47:14.
                      </term> at 47:14.
                    </simple> at 47:14.
                  </expr> at 47:14.
                  <statements> at 47:16.
                    <statement> at 47:16.
                      <output> at 47:16.
                      </output> at 48:3.
                    </statement> at 48:3.
                  </statements> at 48:3.
                  </elif> at 48:3.
                  <elif> at 48:3.
                  <expr> at 48:8.
                    <simple> at 48:8.
                      <term> at 48:8.
                        <factor> at 48:8.
                        </factor> at 48:10.
                      </term> at 48:10.
                    </simple> at 48:10.
                    <simple> at 48:12.
                      <term> at 48:12.
                        <factor> at 48:12.
                        </factor> at 48:14.
                      </term> at 48:14.
                    </simple> at 48:14.
                  </expr> at 48:14.
                  <statements> at 48:16.
                    <statement> at 48:16.
                      <output> at 48:16.
                      </output> at 49:3.
                    </statement> at 49:3.
                  </statements> at 49:3.
                  </elif> at 49:3.
                  <elif> at 49:3.
                  <expr> at 49:8.
                    <simple> at 49:8.
                      <term> at 49:8.
                        <factor> at 49:8.
                        </factor> at 49:10.
                      </term> at 49:10.
                    </simple> at 49:10.
                    <simple> at 49:12.
                      <term> at 49:12.
                        <factor> at 49:12.
                        </factor> at 49:14.
                      </term> at 49:14.
                    </simple> at 49:14.
                  </expr> at 49:14.
                  <statements> at 49:16.
                    <statement> at 49:16.
                      <output> at 49:16.
                      </output> at 50:3.
                    </statement> at 50:3.
                  </statements> at 50:3.
                  </elif> at 50:3.
                  <elif> at 50:3.
                  <expr> at 50:8.
                    <simple> at 50:8.
                      <term> at 50:8.
                        <factor> at 50:8.
                        </factor> at 50:10.
                      </term> at 50:10.
                    </simple> at 50:10.
                    <simple> at 50:12.
                      <term> at 50:12.
                        <factor> at 50:12.
                        </factor> at 50:14.
                      </term> at 50:14.
                    </simple> at 50:14.
                  </expr> at 50:14.
                  <statements> at 50:16.
                    <statement> at 50:16.
                      <output> at 50:16.
                      </output> at 51:3.
                    </statement> at 51:3.
                  </statements> at 51:3.
                  </elif> at 51:3.
                  <elif> at 51:3.
                  <expr> at 51:8.
                    <simple> at 51:8.
                      <term> at 51:8.
                        <factor> at 51:8.
                        </factor> at 51:10.
                      </term> at 51:10.
                    </simple> at 51:10.
                    <simple> at 51:12.
                      <term> at 51:12.
                        <factor> at 51:12.
                        </factor> at 51:14.
                      </term> at 51:14.
                    </simple> at 51:14.
                  </expr> at 51:14.
                  <statements> at 51:16.
                    <statement> at 51:16.
                      <output> at 51:16.
                      </output> at 52:3.
                    </statement> at 52:3.
                  </statements> at 52:3.
                  </elif> at 52:3.
                  <elif> at 52:3.
                  <expr> at 52:8.
                    <simple> at 52:8.
                      <term> at 52:8.
                        <factor> at 52:8.
                        </factor> at 52:10.
                      </term> at 52:10.
                    </simple> at 52:10.
                    <simple> at 52:12.
                      <term> at 52:12.
                        <factor> at 52:12.
                        </factor> at 52:14.
                      </term> at 52:14.
                    </simple> at 52:14.
                  </expr> at 52:14.
                  <statements> at 52:16.
                    <statement> at 52:16.
                      <output> at 52:16.
                      </output> at 53:3.
                    </statement> at 53:3.
                  </statements> at 53:3.
                  </elif> at 53:3.
                  <elif> at 53:3.
                  <expr> at 53:8.
                    <simple> at 53:8.
                      <term> at 53:8.
                        <factor> at 53:8.
                        </factor> at 53:10.
                      </term> at 53:10.
                    </simple> at 53:10.
                    <simple> at 53:12.
                      <term> at 53:12.
                        <factor> at 53:12.
                        </factor> at 53:14.
                      </term> at 53:14.
                    </simple> at 53:14.
                  </expr> at 53:14.
                  <statements> at 53:16.
                    <statement> at 53:16.
                      <output> at 53:16.
                      </output> at 54:3.
                    </statement> at 54:3.
                  </statements> at 54:3.
                  </elif> at 54:3.
                  <elif> at 54:3.
                  <expr> at 54:8.
                    <simple> at 54:8.
                      <term> at 54:8.
                        <factor> at 54:8.
                        </factor> at 54:10.
                      </term> at 54:10.
                    </simple> at 54:10.
                    <simple> at 54:12.
                      <term> at 54:12.
                        <factor> at 54:12.
                        </factor> at 54:14.
                      </term> at 54:14.
                    </simple> at 54:14.
                  </expr> at 54:14.
                  <statements> at 54:16.
                    <statement> at 54:16.
                      <output> at 54:16.
                      </output> at 55:3.
                    </statement> at 55:3.
                  </statements> at 55:3.
                  </elif> at 55:3.
                  <elif> at 55:3.
                  <expr> at 55:8.
                    <simple> at 55:8.
                      <term> at 55:8.
                        <factor> at 55:8.
                        </factor> at 55:10.
                      </term> at 55:10.
                    </simple> at 55:10.
                    <simple> at 55:12.
                      <term> at 55:12.
                        <factor> at 55:12.
                        </factor> at 55:14.
                      </term> at 55:14.
                    </simple> at 55:14.
                  </expr> at 55:14.
                  <statements> at 55:16.
                    <statement> at 55:16.
                      <output> at 55:16.
                      </output> at 56:3.
                    </statement> at 56:3.
                  </statements> at 56:3.
                  </elif> at 56:3.
                  <elif> at 56:3.
                  <expr> at 56:8.
                    <simple> at 56:8.
                      <term> at 56:8.
                        <factor> at 56:8.
                        </factor> at 56:10.
                      </term> at 56:10.
                    </simple> at 56:10.
                    <simple> at 56:12.
                      <term> at 56:12.
                        <factor> at 56:12.
                        </factor> at 56:14.
                      </term> at 56:14.
                    </simple> at 56:14.
                  </expr> at 56:14.
                  <statements> at 56:16.
                    <statement> at 56:16.
                      <output> at 56:16.
                      </output> at 57:3.
                    </statement> at 57:3.
                  </statements> at 57:3.
                  </elif> at 57:3.
                  <elif> at 57:3.
                  <expr> at 57:8.
                    <simple> at 57:8.
                      <term> at 57:8.
                        <factor> at 57:8.
                        </factor> at 57:10.
                      </term> at 57:10.
                    </simple> at 57:10.
                    <simple> at 57:12.
                      <term> at 57:12.
                        <factor> at 57:12.
                        </factor> at 57:14.
                      </term> at 57:14.
                    </simple> at 57:14.
                  </expr> at 57:14.
                  <statements> at 57:16.
                    <statement> at 57:16.
                      <output> at 57:16.
                      </output> at 58:3.
                    </statement> at 58:3.
                  </statements> at 58:3.
                  </elif> at 58:3.
                  <elif> at 58:3.
                  <expr> at 58:8.
                    <simple> at 58:8.
                      <term> at 58:8.
                        <factor> at 58:8.
                        </factor> at 58:10.
                      </term> at 58:10.
                    </simple> at 58:10.
                    <simple> at 58:12.
                      <term> at 58:12.
                        <factor> at 58:12.
                        </factor> at 58:14.
                      </term> at 58:14.
                    </simple> at 58:14.
                  </expr> at 58:14.
                  <statements> at 58:16.
                    <statement> at 58:16.
                      <output> at 58:16.
                      </output> at 59:3.
                    </statement> at 59:3.
                  </statements> at 59:3.
                  </elif> at 59:3.
                  <elif> at 59:3.
                  <expr> at 59:8.
                    <simple> at 59:8.
                      <term> at 59:8.
                        <factor> at 59:8.
                        </factor> at 59:10.
                      </term> at 59:10.
                    </simple> at 59:10.
                    <simple> at 59:12.
                      <term> at 59:12.
                        <factor> at 59:12.
                        </factor> at 59:14.
                      </term> at 59:14.
                    </simple> at 59:14.
                  </expr> at 59:14.
                  <statements> at 59:16.
                    <statement> at 59:16.
                      <output> at 59:16.
                      </output> at 60:3.
                    </statement> at 60:3.
                  </statements> at 60:3.
                  </elif> at 60:3.
                  <elif> at 60:3.
                  <expr> at 60:8.
                    <simple> at 60:8.
                      <term> at 60:8.
                        <factor> at 60:8.
                        </factor> at 60:10.
                      </term> at 60:10.
                    </simple> at 60:10.
                    <simple> at 60:12.
                      <term> at 60:12.
                        <factor> at 60:12.
                        </factor> at 60:14.
                      </term> at 60:14.
                    </simple> at 60:14.
                  </expr> at 60:14.
                  <statements> at 60:16.
                    <statement> at 60:16.
                      <output> at 60:16.
                      </output> at 61:3.
                    </statement> at 61:3.
                  </statements> at 61:3.
                  </elif> at 61:3.
                  <elif> at 61:3.
                  <expr> at 61:8.
                    <simple> at 61:8.
                      <term> at 61:8.
                        <factor> at 61:8.
                        </factor> at 61:10.
                      </term> at 61:10.
                    </simple> at 61:10.
                    <simple> at 61:12.
                      <term> at 61:12.
                        <factor> at 61:12.
                        </factor> at 61:14.
                      </term> at 61:14.
                    </simple> at 61:14.
                  </expr> at 61:14.
                  <statements> at 61:16.
                    <statement> at 61:16.
                      <output> at 61:16.
                      </output> at 62:3.
                    </statement> at 62:3.
                  </statements> at 62:3.
                  </elif> at 62:3.
                  <elif> at 62:3.
                  <expr> at 62:8.
                    <simple> at 62:8.
                      <term> at 62:8.
                        <factor> at 62:8.
                        </factor> at 62:10.
                      </term> at 62:10.
                    </simple> at 62:10.
                    <simple> at 62:12.
                      <term> at 62:12.
                        <factor> at 62:12.
                        </factor> at 62:14.
                      </term> at 62:14.
                    </simple> at 62:14.
                  </expr> at 62:14.
                  <statements> at 62:16.
                    <statement> at 62:16.
                      <output> at 62:16.
                      </output> at 63:3.
                    </statement> at 63:3.
                  </statements> at 63:3.
                  </elif> at 63:3.
                  <elif> at 63:3.
                  <expr> at 63:8.
                    <simple> at 63:8.
                      <term> at 63:8.
                        <factor> at 63:8.
                        </factor> at 63:10.
                      </term> at 63:10.
                    </simple> at 63:10.
                    <simple> at 63:12.
                      <term> at 63:12.
                        <factor> at 63:12.
                        </factor> at 63:14.
                      </term> at 63:14.
                    </simple> at 63:14.
                  </expr> at 63:14.
                  <statements> at 63:16.
                    <statement> at 63:16.
                      <output> at 63:16.
                      </output> at 64:3.
                    </statement> at 64:3.
                  </statements> at 64:3.
                  </elif> at 64:3.
                  <elif> at 64:3.
                  <expr> at 64:8.
                    <simple> at 64:8.
                      <term> at 64:8.
                        <factor> at 64:8.
                        </factor> at 64:10.
                      </term> at 64:10.
                    </simple> at 64:10.
                    <simple> at 64:12.
                      <term> at 64:12.
                        <factor> at 64:12.
                        </factor> at 64:14.
                      </term> at 64:14.
                    </simple> at 64:14.
                  </expr> at 64:14.
                  <statements> at 64:16.
                    <statement> at 64:16.
                      <output> at 64:16.
                      </output> at 65:3.
                    </statement> at 65:3.
                  </statements> at 65:3.
                  </elif> at 65:3.
                  <elif> at 65:3.
                  <expr> at 65:8.
                    <simple> at 65:8.
                      <term> at 65:8.
                        <factor> at 65:8.
                        </factor> at 65:10.
                      </term> at 65:10.
                    </simple> at 65:10.
                    <simple> at 65:12.
                      <term> at 65:12.
                        <factor> at 65:12.
                        </factor> at 65:14.
                      </term> at 65:14.
                    </simple> at 65:14.
                  </expr> at 65:14.
                  <statements> at 65:16.
                    <statement> at 65:16.
                      <output> at 65:16.
                      </output> at 66:3.
                    </statement> at 66:3.
                  </statements> at 66:3.
                  </elif> at 66:3.
                  <elif> at 66:3.
                  <expr> at 66:8.
                    <simple> at 66:8.
                      <term> at 66:8.
                        <factor> at 66:8.
                        </factor> at 66:10.
                      </term> at 66:10.
                    </simple> at 66:10.
                    <simple> at 66:12.
                      <term> at 66:12.
                        <factor> at 66:12.
                        </factor> at 66:14.
                      </term> at 66:14.
                    </simple> at 66:14.
                  </expr> at 66:14.
                  <statements> at 66:16.
                    <statement> at 66:16.
                      <output> at 66:16.
                      </output> at 67:3.
                    </statement> at 67:3.
                  </statements> at 67:3.
                  </elif> at 67:3.
                  <elif> at 67:3.
                  <expr> at 67:8.
                    <simple> at 67:8.
                      <term> at 67:8.
                        <factor> at 67:8.
                        </factor> at 67:10.
                      </term> at 67:10.
                    </simple> at 67:10.
                    <simple> at 67:12.
                      <term> at 67:12.
                        <factor> at 67:12.
                        </factor> at 67:14.
                      </term> at 67:14.
                    </simple> at 67:14.
                  </expr> at 67:14.
                  <statements> at 67:16.
                    <statement> at 67:16.
                      <output> at 67:16.
                      </output> at 68:3.
                    </statement> at 68:3.
                  </statements> at 68:3.
                  </elif> at 68:3.
                  <elif> at 68:3.
                  <expr> at 68:8.
                    <simple> at 68:8.
                      <term> at 68:8.
                        <factor> at 68:8.
                        </factor> at 68:10.
                      </term> at 68:10.
                    </simple> at 68:10.
                    <simple> at 68:12.
                      <term> at 68:12.
                        <factor> at 68:12.
                        </factor> at 68:14.
                      </term> at 68:14.
                    </simple> at 68:14.
                  </expr> at 68:14.
                  <statements> at 68:16.
                    <statement> at 68:16.
                      <output> at 68:16.
                      </output> at 69:3.
                    </statement> at 69:3.
                  </statements> at 69:3.
                  </elif> at 69:3.
                  <elif> at 69:3.
                  <expr> at 69:8.
                    <simple> at 69:8.
                      <term> at 69:8.
                        <factor> at 69:8.
                        </factor> at 69:10.
                      </term> at 69:10.
                    </simple> at 69:10.
                    <simple> at 69:12.
                      <term> at 69:12.
                        <factor> at 69:12.
                        </factor> at 69:14.
                      </term> at 69:14.
                    </simple> at 69:14.
                  </expr> at 69:14.
                  <statements> at 69:16.
                    <statement> at 69:16.
                      <output> at 69:16.
                      </output> at 70:3.
                    </statement> at 70:3.
                  </statements> at 70:3.
                  </elif> at 70:3.
                  <elif> at 70:3.
                  <expr> at 70:8.
                    <simple> at 70:8.
                      <term> at 70:8.
                        <factor> at 70:8.
                        </factor> at 70:10.
                      </term> at 70:10.
                    </simple> at 70:10.
                    <simple> at 70:12.
                      <term> at 70:12.
                        <factor> at 70:12.
                        </factor> at 70:14.
                      </term> at 70:14.
                    </simple> at 70:14.
                  </expr> at 70:14.
                  <statements> at 70:16.
                    <statement> at 70:16.
                      <output> at 70:16.
                      </output> at 71:3.
                    </statement> at 71:3.
                  </statements> at 71:3.
                  </elif> at 71:3.
                  <elif> at 71:3.
                  <expr> at 71:8.
                    <simple> at 71:8.
                      <term> at 71:8.
                        <factor> at 71:8.
                        </factor> at 71:10.
                      </term> at 71:10.
                    </simple> at 71:10.
                    <simple> at 71:12.
                      <term> at 71:12.
                        <factor> at 71:12.
                        </factor> at 71:14.
                      </term> at 71:14.
                    </simple> at 71:14.
                  </expr> at 71:14.
                  <statements> at 71:16.
                    <statement> at 71:16.
                      <output> at 71:16.
                      </output> at 72:3.
                    </statement> at 72:3.
                  </statements> at 72:3.
                  </elif> at 72:3.
                  <elif> at 72:3.
                  <expr> at 72:8.
                    <simple> at 72:8.
                      <term> at 72:8.
                        <factor> at 72:8.
                        </factor> at 72:10.
                      </term> at 72:10.
                    </simple> at 72:10.
                    <simple> at 72:12.
                      <term> at 72:12.
                        <factor> at 72:12.
                        </factor> at 72:14.
                      </term> at 72:14.
                    </simple> at 72:14.
                  </expr> at 72:14.
                  <statements> at 72:16.
                    <statement> at 72:16.
                      <output> at 72:16.
                      </output> at 73:3.
                    </statement> at 73:3.
                  </statements> at 73:3.
                  </elif> at 73:3.
                  <elif> at 73:3.
                  <expr> at 73:8.
                    <simple> at 73:8.
                      <term> at 73:8.
                        <factor> at 73:8.
                        </factor> at 73:10.
                      </term> at 73:10.
                    </simple> at 73:10.
                    <simple> at 73:12.
                      <term> at 73:12.
                        <factor> at 73:12.
                        </factor> at 73:14.
                      </term> at 73:14.
                    </simple> at 73:14.
                  </expr> at 73:14.
                  <statements> at 73:16.
                    <statement> at 73:16.
                      <output> at 73:16.
                      </output> at 74:3.
                    </statement> at 74:3.
                  </statements> at 74:3.
                  </elif> at 74:3.
                  <elif> at 74:3.
                  <expr> at 74:8.
                    <simple> at 74:8.
                      <term> at 74:8.
                        <factor> at 74:8.
                        </factor> at 74:10.
                      </term> at 74:10.
                    </simple> at 74:10.
                    <simple> at 74:12.
                      <term> at 74:12.
                        <factor> at 74:12.
                        </factor> at 74:14.
                      </term> at 74:14.
                    </simple> at 74:14.
                  </expr> at 74:14.
                  <statements> at 74:16.
                    <statement> at 74:16.
                      <output> at 74:16.
                      </output> at 75:3.
                    </statement> at 75:3.
                  </statements> at 75:3.
                  </elif> at 75:3.
                  <elif> at 75:3.
                  <expr> at 75:8.
                    <simple> at 75:8.
                      <term> at 75:8.
                        <factor> at 75:8.
                        </factor> at 75:10.
                      </term> at 75:10.
                    </simple> at 75:10.
                    <simple> at 75:12.
                      <term> at 75:12.
                        <factor> at 75:12.
                        </factor> at 75:14.
                      </term> at 75:14.
                    </simple> at 75:14.
                  </expr> at 75:14.
                  <statements> at 75:16.
                    <statement> at 75:16.
                      <output> at 75:16.
                      </output> at 76:3.
                    </statement> at 76:3.
                  </statements> at 76:3.
                  </elif> at 76:3.
                  <elif> at 76:3.
                  <expr> at 76:8.
                    <simple> at 76:8.
                      <term> at 76:8.
                        <factor> at 76:8.
                        </factor> at 76:10.
                      </term> at 76:10.
                    </simple> at 76:10.
                    <simple> at 76:12.
                      <term> at 76:12.
                        <factor> at 76:12.
                        </factor> at 76:14.
                      </term> at 76:14.
                    </simple> at 76:14.
                  </expr> at 76:14.
                  <statements> at 76:16.
                    <statement> at 76:16.
                      <output> at 76:16.
                      </output> at 77:3.
                    </statement> at 77:3.
                  </statements> at 77:3.
                  </elif> at 77:3.
                  <elif> at 77:3.
                  <expr> at 77:8.
                    <simple> at 77:8.
                      <term> at 77:8.
                        <factor> at 77:8.
                        </factor> at 77:10.
                      </term> at 77:10.
                    </simple> at 77:10.
                    <simple> at 77:12.
                      <term> at 77:12.
                        <factor> at 77:12.
                        </factor> at 77:14.
                      </term> at 77:14.
                    </simple> at 77:14.
                  </expr> at 77:14.
                  <statements> at 77:16.
                    <statement> at 77:16.
                      <output> at 77:16.
                      </output> at 78:3.
                    </statement> at 78:3.
                  </statements> at 78:3.
                  </elif> at 78:3.
                  <elif> at 78:3.
                  <expr> at 78:8.
                    <simple> at 78:8.
                      <term> at 78:8.
                        <factor> at 78:8.
                        </factor> at 78:10.
                      </term> at 78:10.
                    </simple> at 78:10.
                    <simple> at 78:12.
                      <term> at 78:12.
                        <factor> at 78:12.
                        </factor> at 78:14.
                      </term> at 78:14.
                    </simple> at 78:14.
                  </expr> at 78:14.
                  <statements> at 78:16.
                    <statement> at 78:16.
                      <output> at 78:16.
                      </output> at 79:3.
                    </statement> at 79:3.
                  </statements> at 79:3.
                  </elif> at 79:3.
                  <elif> at 79:3.
                  <expr> at 79:8.
                    <simple> at 79:8.
                      <term> at 79:8.
                        <factor> at 79:8.
                        </factor> at 79:10.
                      </term> at 79:10.
                    </simple> at 79:10.
                    <simple> at 79:12.
                      <term> at 79:12.
                        <factor> at 79:12.
                        </factor> at 79:14.
                      </term> at 79:14.
                    </simple> at 79:14.
                  </expr> at 79:14.
                  <statements> at 79:16.
                    <statement> at 79:16.
                      <output> at 79:16.
                      </output> at 80:3.
                    </statement> at 80:3.
                  </statements> at 80:3.
                  </elif> at 80:3.
                  <elif> at 80:3.
                  <expr> at 80:8.
                    <simple> at 80:8.
                      <term> at 80:8.
                        <factor> at 80:8.
                        </factor> at 80:10.
                      </term> at 80:10.
                    </simple> at 80:10.
                    <simple> at 80:12.
                      <term> at 80:12.
                        <factor> at 80:12.
                        </factor> at 80:14.
                      </term> at 80:14.
                    </simple> at 80:14.
                  </expr> at 80:14.
                  <statements> at 80:16.
                    <statement> at 80:16.
                      <output> at 80:16.
                      </output> at 81:3.
                    </statement> at 81:3.
                  </statements> at 81:3.
                  </elif> at 81:3.
                  <elif> at 81:3.
                  <expr> at 81:8.
                    <simple> at 81:8.
                      <term> at 81:8.
                        <factor> at 81:8.
                        </factor> at 81:10.
                      </term> at 81:10.
                    </simple> at 81:10.
                    <simple> at 81:12.
                      <term> at 81:12.
                        <factor> at 81:12.
                        </factor> at 81:14.
                      </term> at 81:14.
                    </simple> at 81:14.
                  </expr> at 81:14.
                  <statements> at 81:16.
                    <statement> at 81:16.
                      <output> at 81:16.
                      </output> at 82:3.
                    </statement> at 82:3.
                  </statements> at 82:3.
                  </elif> at 82:3.
                  <elif> at 82:3.
                  <expr> at 82:8.
                    <simple> at 82:8.
                      <term> at 82:8.
                        <factor> at 82:8.
                        </factor> at 82:10.
                      </term> at 82:10.
                    </simple> at 82:10.
                    <simple> at 82:12.
                      <term> at 82:12.
                        <factor> at 82:12.
                        </factor> at 82:14.
                      </term> at 82:14.
                    </simple> at 82:14.
                  </expr> at 82:14.
                  <statements> at 82:16.
                    <statement> at 82:16.
                      <output> at 82:16.
                      </output> at 83:3.
                    </statement> at 83:3.
                  </statements> at 83:3.
                  </elif> at 83:3.
                  <elif> at 83:3.
                  <expr> at 83:8.
                    <simple> at 83:8.
                      <term> at 83:8.
                        <factor> at 83:8.
                        </factor> at 83:10.
                      </term> at 83:10.
                    </simple> at 83:10.
                    <simple> at 83:12.
                      <term> at 83:12.
                        <factor> at 83:12.
                        </factor> at 83:14.
                      </term> at 83:14.
                    </simple> at 83:14.
                  </expr> at 83:14.
                  <statements> at 83:16.
                    <statement> at 83:16.
                      <output> at 83:16.
                      </output> at 84:3.
                    </statement> at 84:3.
                  </statements> at 84:3.
                  </elif> at 84:3.
                  <elif> at 84:3.
                  <expr> at 84:8.
                    <simple> at 84:8.
                      <term> at 84:8.
                        <factor> at 84:8.
                        </factor> at 84:10.
                      </term> at 84:10.
                    </simple> at 84:10.
                    <simple> at 84:12.
                      <term> at 84:12.
                        <factor> at 84:12.
                        </factor> at 84:14.
                      </term> at 84:14.
                    </simple> at 84:14.
                  </expr> at 84:14.
                  <statements> at 84:16.
                    <statement> at 84:16.
                      <output> at 84:16.
                      </output> at 85:3.
                    </statement> at 85:3.
                  </statements> at 85:3.
                  </elif> at 85:3.
                  <elif> at 85:3.
                  <expr> at 85:8.
                    <simple> at 85:8.
                      <term> at 85:8.
                        <factor> at 85:8.
                        </factor> at 85:10.
                      </term> at 85:10.
                    </simple> at 85:10.
                    <simple> at 85:12.
                      <term> at 85:12.
                        <factor> at 85:12.
                        </factor> at 85:14.
                      </term> at 85:14.
                    </simple> at 85:14.
                  </expr> at 85:14.
                  <statements> at 85:16.
                    <statement> at 85:16.
                      <output> at 85:16.
                      </output> at 86:3.
                    </statement> at 86:3.
                  </statements> at 86:3.
                  </elif> at 86:3.
                  <elif> at 86:3.
                  <expr> at 86:8.
                    <simple> at 86:8.
                      <term> at 86:8.
                        <factor> at 86:8.
                        </factor> at 86:10.
                      </term> at 86:10.
                    </simple> at 86:10.
                    <simple> at 86:12.
                      <term> at 86:12.
                        <factor> at 86:12.
                        </factor> at 86:14.
                      </term> at 86:14.
                    </simple> at 86:14.
                  </expr> at 86:14.
                  <statements> at 86:16.
                    <statement> at 86:16.
                      <output> at 86:16.
                      </output> at 87:3.
                    </statement> at 87:3.
                  </statements> at 87:3.
                  </elif> at 87:3.
                  <elif> at 87:3.
                  <expr> at 87:8.
                    <simple> at 87:8.
                      <term> at 87:8.
                        <factor> at 87:8.
                        </factor> at 87:10.
                      </term> at 87:10.
                    </simple> at 87:10.
                    <simple> at 87:12.
                      <term> at 87:12.
                        <factor> at 87:12.
                        </factor> at 87:14.
                      </term> at 87:14.
                    </simple> at 87:14.
                  </expr> at 87:14.
                  <statements> at 87:16.
                    <statement> at 87:16.
                      <output> at 87:16.
                      </output> at 88:3.
                    </statement> at 88:3.
                  </statements> at 88:3.
                  </elif> at 88:3.
                  <elif> at 88:3.
                  <expr> at 88:8.
                    <simple> at 88:8.
                      <term> at 88:8.
                        <factor> at 88:8.
                        </factor> at 88:10.
                      </term> at 88:10.
                    </simple> at 88:10.
                    <simple> at 88:12.
                      <term> at 88:12.
                        <factor> at 88:12.
                        </factor> at 88:14.
                      </term> at 88:14.
                    </simple> at 88:14.
                  </expr> at 88:14.
                  <statements> at 88:16.
                    <statement> at 88:16.
                      <output> at 88:16.
                      </output> at 89:3.
                    </statement> at 89:3.
                  </statements> at 89:3.
                  </elif> at 89:3.
                  <elif> at 89:3.
                  <expr> at 89:8.
                    <simple> at 89:8.
                      <term> at 89:8.
                        <factor> at 89:8.
                        </factor> at 89:10.
                      </term> at 89:10.
                    </simple> at 89:10.
                    <simple> at 89:12.
                      <term> at 89:12.
                        <factor> at 89:12.
                        </factor> at 89:14.
                      </term> at 89:14.
                    </simple> at 89:14.
                  </expr> at 89:14.
                  <statements> at 89:16.
                    <statement> at 89:16.
                      <output> at 89:16.
                      </output> at 90:3.
                    </statement> at 90:3.
                  </statements> at 90:3.
                  </elif> at 90:3.
                  <elif> at 90:3.
                  <expr> at 90:8.
                    <simple> at 90:8.
                      <term> at 90:8.
                        <factor> at 90:8.
                        </factor> at 90:10.
                      </term> at 90:10.
                    </simple> at 90:10.
                    <simple> at 90:12.
                      <term> at 90:12.
                        <factor> at 90:12.
                        </factor> at 90:14.
                      </term> at 90:14.
                    </simple> at 90:14.
                  </expr> at 90:14.
                  <statements> at 90:16.
                    <statement> at 90:16.
                      <output> at 90:16.
                      </output> at 91:3.
                    </statement> at 91:3.
                  </statements> at 91:3.
                  </elif> at 91:3.
                  <elif> at 91:3.
                  <expr> at 91:8.
                    <simple> at 91:8.
                      <term> at 91:8.
                        <factor> at 91:8.
                        </factor> at 91:10.
                      </term> at 91:10.
                    </simple> at 91:10.
                    <simple> at 91:12.
                      <term> at 91:12.
                        <factor> at 91:12.
                        </factor> at 91:14.
                      </term> at 91:14.
                    </simple> at 91:14.
                  </expr> at 91:14.
                  <statements> at 91:16.
                    <statement> at 91:16.
                      <output> at 91:16.
                      </output> at 92:3.
                    </statement> at 92:3.
                  </statements> at 92:3.
                  </elif> at 92:3.
                  <elif> at 92:3.
                  <expr> at 92:8.
                    <simple> at 92:8.
                      <term> at 92:8.
                        <factor> at 92:8.
                        </factor> at 92:10.
                      </term> at 92:10.
                    </simple> at 92:10.
                    <simple> at 92:12.
                      <term> at 92:12.
                        <factor> at 92:12.
                        </factor> at 92:14.
                      </term> at 92:14.
                    </simple> at 92:14.
                  </expr> at 92:14.
                  <statements> at 92:16.
                    <statement> at 92:16.
                      <output> at 92:16.
                      </output> at 93:3.
                    </statement> at 93:3.
                  </statements> at 93:3.
                  </elif> at 93:3.
                  <elif> at 93:3.
                  <expr> at 93:8.
                    <simple> at 93:8.
                      <term> at 93:8.
                        <factor> at 93:8.
                        </factor> at 93:10.
                      </term> at 93:10.
                    </simple> at 93:10.
                    <simple> at 93:12.
                      <term> at 93:12.
                        <factor> at 93:12.
                        </factor> at 93:14.
                      </term> at 93:14.
                    </simple> at 93:14.
                  </expr> at 93:14.
                  <statements> at 93:16.
                    <statement> at 93:16.
                      <output> at 93:16.
                      </output> at 94:3.
                    </statement> at 94:3.
                  </statements> at 94:3.
                  </elif> at 94:3.
                  <elif> at 94:3.
                  <expr> at 94:8.
                    <simple> at 94:8.
                      <term> at 94:8.
                        <factor> at 94:8.
                        </factor> at 94:10.
                      </term> at 94:10.
                    </simple> at 94:10.
                    <simple> at 94:12.
                      <term> at 94:12.
                        <factor> at 94:12.
                        </factor> at 94:14.
                      </term> at 94:14.
                    </simple> at 94:14.
                  </expr> at 94:14.
                  <statements> at 94:16.
                    <statement> at 94:16.
                      <output> at 94:16.
                      </output> at 95:3.
                    </statement> at 95:3.
                  </statements> at 95:3.
                  </elif> at 95:3.
                  <elif> at 95:3.
                  <expr> at 95:8.
                    <simple> at 95:8.
                      <term> at 95:8.
                        <factor> at 95:8.
                        </factor> at 95:10.
                      </term> at 95:10.
                    </simple> at 95:10.
                    <simple> at 95:12.
                      <term> at 95:12.
                        <factor> at 95:12.
                        </factor> at 95:14.
                      </term> at 95:14.
                    </simple> at 95:14.
                  </expr> at 95:14.
                  <statements> at 95:16.
                    <statement> at 95:16.
                      <output> at 95:16.
                      </output> at 96:3.
                    </statement> at 96:3.
                  </statements> at 96:3.
                  </elif> at 96:3.
                  <elif> at 96:3.
                  <expr> at 96:8.
                    <simple> at 96:8.
                      <term> at 96:8.
                        <factor> at 96:8.
                        </factor> at 96:10.
                      </term> at 96:10.
                    </simple> at 96:10.
                    <simple> at 96:12.
                      <term> at 96:12.
                        <factor> at 96:12.
                        </factor> at 96:14.
                      </term> at 96:14.
                    </simple> at 96:14.
                  </expr> at 96:14.
                  <statements> at 96:16.
                    <statement> at 96:16.
                      <output> at 96:16.
                      </output> at 97:3.
                    </statement> at 97:3.
                  </statements> at 97:3.
                  </elif> at 97:3.
                  <elif> at 97:3.
                  <expr> at 97:8.
                    <simple> at 97:8.
                      <term> at 97:8.
                        <factor> at 97:8.
                        </factor> at 97:10.
                      </term> at 97:10.
                    </simple> at 97:10.
                    <simple> at 97:12.
                      <term> at 97:12.
                        <factor> at 97:12.
                        </factor> at 97:14.
                      </term> at 97:14.
                    </simple> at 97:14.
                  </expr> at 97:14.
                  <statements> at 97:16.
                    <statement> at 97:16.
                      <output> at 97:16.
                      </output> at 98:3.
                    </statement> at 98:3.
                  </statements> at 98:3.
                  </elif> at 98:3.
                  <elif> at 98:3.
                  <expr> at 98:8.
                    <simple> at 98:8.
                      <term> at 98:8.
                        <factor> at 98:8.
                        </factor> at 98:10.
                      </term> at 98:10.
                    </simple> at 98:10.
                    <simple> at 98:12.
                      <term> at 98:12.
                        <factor> at 98:12.
                        </factor> at 98:14.
                      </term> at 98:14.
                    </simple> at 98:14.
                  </expr> at 98:14.
                  <statements> at 98:16.
                    <statement> at 98:16.
                      <output> at 98:16.
                      </output> at 99:3.
                    </statement> at 99:3.
                  </statements> at 99:3.
                  </elif> at 99:3.
                  <elif> at 99:3.
                  <expr> at 99:8.
                    <simple> at 99:8.
                      <term> at 99:8.
                        <factor> at 99:8.
                        </factor> at 99:10.
                      </term> at 99:10.
                    </simple> at 99:10.
                    <simple> at 99:12.
                      <term> at 99:12.
                        <factor> at 99:12.
                        </factor> at 99:14.
                      </term> at 99:14.
                    </simple> at 99:14.
                  </expr> at 99:14.
                  <statements> at 99:16.
                    <statement> at 99:16.
                      <output> at 99:16.
                      </output> at 100:3.
                    </statement> at 100:3.
                  </statements> at 100:3.
                  </elif> at 100:3.
                  <elif> at 100:3.
                  <expr> at 100:8.
                    <simple> at 100:8.
                      <term> at 100:8.
                        <factor> at 100:8.
                        </factor> at 100:10.
                      </term> at 100:10.
                    </simple> at 100:10.
                    <simple> at 100:12.
                      <term> at 100:12.
                        <factor> at 100:12.
                        </factor> at 100:14.
                      </term> at 100:14.
                    </simple> at 100:14.
                  </expr> at 100:14.
                  <statements> at 100:16.
                    <statement> at 100:16.
                      <output> at 100:16.
                      </output> at 101:3.
                    </statement> at 101:3.
                  </statements> at 101:3.
                  </elif> at 101:3.
                  <elif> at 101:3.
                  <expr> at 101:8.
                    <simple> at 101:8.
                      <term> at 101:8.
                        <factor> at 101:8.
                        </factor> at 101:10.
                      </term> at 101:10.
                    </simple> at 101:10.
                    <simple> at 101:12.
                      <term> at 101:12.
                        <factor> at 101:12.
                        </factor> at 101:14.
                      </term> at 101:14.
                    </simple> at 101:14.
                  </expr> at 101:14.
                  <statements> at 101:16.
                    <statement> at 101:16.
                      <output> at 101:16.
                      </output> at 102:3.
                    </statement> at 102:3.
                  </statements> at 102:3.
                  </elif> at 102:3.
                  <elif> at 102:3.
                  <expr> at 102:8.
                    <simple> at 102:8.
                      <term> at 102:8.
                        <factor> at 102:8.
                        </factor> at 102:10.
                      </term> at 102:10.
                    </simple> at 102:10.
                    <simple> at 102:12.
                      <term> at 102:12.
                        <factor> at 102:12.
                        </factor> at 102:14.
                      </term> at 102:14.
                    </simple> at 102:14.
                  </expr> at 102:14.
                  <statements> at 102:16.
                    <statement> at 102:16.
                      <output> at 102:16.
                      </output> at 103:3.
                    </statement> at 103:3.
                  </statements> at 103:3.
                  </elif> at 103:3.
                  <elif> at 103:3.
                  <expr> at 103:8.
                    <simple> at 103:8.
                      <term> at 103:8.
                        <factor> at 103:8.
                        </factor> at 103:10.
                      </term> at 103:10.
                    </simple> at 103:10.
                    <simple> at 103:12.
                      <term> at 103:12.
                        <factor> at 103:12.
                        </factor> at 103:14.
                      </term> at 103:14.
                    </simple> at 103:14.
                  </expr> at 103:14.
                  <statements> at 103:16.
                    <statement> at 103:16.
                      <output> at 103:16.
                      </output> at 104:3.
                    </statement> at 104:3.
                  </statements> at 104:3.
                  </elif> at 104:3.
                  <elif> at 104:3.
                  <expr> at 104:8.
                    <simple> at 104:8.
                      <term> at 104:8.
                        <factor> at 104:8.
                        </factor> at 104:10.
                      </term> at 104:10.
                    </simple> at 104:10.
                    <simple> at 104:12.
                      <term> at 104:12.
                        <factor> at 104:12.
                        </factor> at 104:14.
                      </term> at 104:14.
                    </simple> at 104:14.
                  </expr> at 104:14.
                  <statements> at 104:16.
                    <statement> at 104:16.
                      <output> at 104:16.
                      </output> at 105:3.
                    </statement> at 105:3.
                  </statements> at 105:3.
                  </elif> at 105:3.
                  <elif> at 105:3.
                  <expr> at 105:8.
                    <simple> at 105:8.
                      <term> at 105:8.
                        <factor> at 105:8.
                        </factor> at 105:10.
                      </term> at 105:10.
                    </simple> at 105:10.
                    <simple> at 105:12.
                      <term> at 105:12.
                        <factor> at 105:12.
                        </factor> at 105:14.
                      </term> at 105:14.
                    </simple> at 105:14.
                  </expr> at 105:14.
                  <statements> at 105:16.
                    <statement> at 105:16.
                      <output> at 105:16.
                      </output> at 106:3.
                    </statement> at 106:3.
                  </statements> at 106:3.
                  </elif> at 106:3.
                  <elif> at 106:3.
                  <expr> at 106:8.
                    <simple> at 106:8.
                      <term> at 106:8.
                        <factor> at 106:8.
                        </factor> at 106:10.
                      </term> at 106:10.
                    </simple> at 106:10.
                    <simple> at 106:12.
                      <term> at 106:12.
                        <factor> at 106:12.
                        </factor> at 106:14.
                      </term> at 106:14.
                    </simple> at 106:14.
                  </expr> at 106:14.
                  <statements> at 106:16.
                    <statement> at 106:16.
                      <output> at 106:16.
                      </output> at 107:3.
                    </statement> at 107:3.
                  </statements> at 107:3.
                  </elif> at 107:3.
                  <elif> at 107:3.
                  <expr> at 107:8.
                    <simple> at 107:8.
                      <term> at 107:8.
                        <factor> at 107:8.
                        </factor> at 107:10.
                      </term> at 107:10.
                    </simple> at 107:10.
                    <simple> at 107:12.
                      <term> at 107:12.
                        <factor> at 107:12.
                        </factor> at 107:14.
                      </term> at 107:14.
                    </simple> at 107:14.
                  </expr> at 107:14.
                  <statements> at 107:16.
                    <statement> at 107:16.
                      <output> at 107:16.
                      </output> at 108:3.
                    </statement> at 108:3.
                  </statements> at 108:3.
                  </elif> at 108:3.
                  <elif> at 108:3.
                  <expr> at 108:8.
                    <simple> at 108:8.
                      <term> at 108:8.
                        <factor> at 108:8.
                        </factor> at 108:10.
                      </term> at 108:10.
                    </simple> at 108:10.
                    <simple> at 108:12.
                      <term> at 108:12.
                        <factor> at 108:12.
                        </factor> at 108:14.
                      </term> at 108:14.
                    </simple> at 108:14.
                  </expr> at 108:14.
                  <statements> at 108:16.
                    <statement> at 108:16.
                      <output> at 108:16.
                      </output> at 109:3.
                    </statement> at 109:3.
                  </statements> at 109:3.
                  </elif> at 109:3.
                  <elif> at 109:3.
                  <expr> at 109:8.
                    <simple> at 109:8.
                      <term> at 109:8.
                        <factor> at 109:8.
                        </factor> at 109:10.
                      </term> at 109:10.
                    </simple> at 109:10.
                    <simple> at 109:12.
                      <term> at 109:12.
                        <factor> at 109:12.
                        </factor> at 109:14.
                      </term> at 109:14.
                    </simple> at 109:14.
                  </expr> at 109:14.
                  <statements> at 109:16.
                    <statement> at 109:16.
                      <output> at 109:16.
                      </output> at 110:3.
                    </statement> at 110:3.
                  </statements> at 110:3.
                  </elif> at 110:3.
                  <elif> at 110:3.
                  <expr> at 110:8.
                    <simple> at 110:8.
                      <term> at 110:8.
                        <factor> at 110:8.
                        </factor> at 110:10.
                      </term> at 110:10.
                    </simple> at 110:10.
                    <simple> at 110:12.
                      <term> at 110:12.
                        <factor> at 110:12.
                        </factor> at 110:15.
                      </term> at 110:15.
                    </simple> at 110:15.
                  </expr> at 110:15.
                  <statements> at 110:17.
                    <statement> at 110:17.
                      <output> at 110:17.
                      </output> at 111:3.
                    </statement> at 111:3.
                  </statements> at 111:3.
                  </elif> at 111:3.
                  <elif> at 111:3.
                  <expr> at 111:8.
                    <simple> at 111:8.
                      <term> at 111:8.
                        <factor> at 111:8.
                        </factor> at 111:10.
                      </term> at 111:10.
                    </simple> at 111:10.
                    <simple> at 111:12.
                      <term> at 111:12.
                        <factor> at 111:12.
                        </factor> at 111:15.
                      </term> at 111:15.
                    </simple> at 111:15.
                  </expr> at 111:15.
                  <statements> at 111:17.
                    <statement> at 111:17.
                      <output> at 111:17.
                      </output> at 112:3.
                    </statement> at 112:3.
                  </statements> at 112:3.
                  </elif> at 112:3.
                  <elif> at 112:3.
                  <expr> at 112:8.
                    <simple> at 112:8.
                      <term> at 112:8.
                        <factor> at 112:8.
                        </factor> at 112:10.
                      </term> at 112:10.
                    </simple> at 112:10.
                    <simple> at 112:12.
                      <term> at 112:12.
                        <factor> at 112:12.
                        </factor> at 112:15.
                      </term> at 112:15.
                    </simple> at 112:15.
                  </expr> at 112:15.
                  <statements> at 112:17.
                    <statement> at 112:17.
                      <output> at 112:17.
                      </output> at 113:3.
                    </statement> at 113:3.
                  </statements> at 113:3.
                  </elif> at 113:3.
                  <elif> at 113:3.
                  <expr> at 113:8.
                    <simple> at 113:8.
                      <term> at 113:8.
                        <factor> at 113:8.
                        </factor> at 113:10.
                      </term> at 113:10.
                    </simple> at 113:10.
                    <simple> at 113:12.
                      <term> at 113:12.
                        <factor> at 113:12.
                        </factor> at 113:15.
                      </term> at 113:15.
                    </simple> at 113:15.
                  </expr> at 113:15.
                  <statements> at 113:17.
                    <statement> at 113:17.
                      <output> at 113:17.
                      </output> at 114:3.
                    </statement> at 114:3.
                  </statements> at 114:3.
                  </elif> at 114:3.
                  <elif> at 114:3.
                  <expr> at 114:8.
                    <simple> at 114:8.
                      <term> at 114:8.
                        <factor> at 114:8.
                        </factor> at 114:10.
                      </term> at 114:10.
                    </simple> at 114:10.
                    <simple> at 114:12.
                      <term> at 114:12.
                        <factor> at 114:12.
                        </factor> at 114:15.
                      </term> at 114:15.
                    </simple> at 114:15.
                  </expr> at 114:15.
                  <statements> at 114:17.
                    <statement> at 114:17.
                      <output> at 114:17.
                      </output> at 115:3.
                    </statement> at 115:3.
                  </statements> at 115:3.
                  </elif> at 115:3.
                  <elif> at 115:3.
                  <expr> at 115:8.
                    <simple> at 115:8.
                      <term> at 115:8.
                        <factor> at 115:8.
                        </factor> at 115:10.
                      </term> at 115:10.
                    </simple> at 115:10.
                    <simple> at 115:12.
                      <term> at 115:12.
                        <factor> at 115:12.
                        </factor> at 115:15.
                      </term> at 115:15.
                    </simple> at 115:15.
                  </expr> at 115:15.
                  <statements> at 115:17.
                    <statement> at 115:17.
                      <output> at 115:17.
                      </output> at 116:3.
                    </statement> at 116:3.
                  </statements> at 116:3.
                  </elif> at 116:3.
                  <elif> at 116:3.
                  <expr> at 116:8.
                    <simple> at 116:8.
                      <term> at 116:8.
                        <factor> at 116:8.
                        </factor> at 116:10.
                      </term> at 116:10.
                    </simple> at 116:10.
                    <simple> at 116:12.
                      <term> at 116:12.
                        <factor> at 116:12.
                        </factor> at 116:15.
                      </term> at 116:15.
                    </simple> at 116:15.
                  </expr> at 116:15.
                  <statements> at 116:17.
                    <statement> at 116:17.
                      <output> at 116:17.
                      </output> at 117:3.
                    </statement> at 117:3.
                  </statements> at 117:3.
                  </elif> at 117:3.
                  <elif> at 117:3.
                  <expr> at 117:8.
                    <simple> at 117:8.
                      <term> at 117:8.
                        <factor> at 117:8.
                        </factor> at 117:10.
                      </term> at 117:10.
                    </simple> at 117:10.
                    <simple> at 117:12.
                      <term> at 117:12.
                        <factor> at 117:12.
                        </factor> at 117:15.
                      </term> at 117:15.
                    </simple> at 117:15.
                  </expr> at 117:15.
                  <statements> at 117:17.
                    <statement> at 117:17.
                      <output> at 117:17.
                      </output> at 118:3.
                    </statement> at 118:3.
                  </statements> at 118:3.
                  </elif> at 118:3.
                  <elif> at 118:3.
                  <expr> at 118:8.
                    <simple> at 118:8.
                      <term> at 118:8.
                        <factor> at 118:8.
                        </factor> at 118:10.
                      </term> at 118:10.
                    </simple> at 118:10.
                    <simple> at 118:12.
                      <term> at 118:12.
                        <factor> at 118:12.
                        </factor> at 118:15.
                      </term> at 118:15.
                    </simple> at 118:15.
                  </expr> at 118:15.
                  <statements> at 118:17.
                    <statement> at 118:17.
                      <output> at 118:17.
                      </output> at 119:3.
                    </statement> at 119:3.
                  </statements> at 119:3.
                  </elif> at 119:3.
                  <elif> at 119:3.
                  <expr> at 119:8.
                    <simple> at 119:8.
                      <term> at 119:8.
                        <factor> at 119:8.
                        </factor> at 119:10.
                      </term> at 119:10.
                    </simple> at 119:10.
                    <simple> at 119:12.
                      <term> at 119:12.
                        <factor> at 119:12.
                        </factor> at 119:15.
                      </term> at 119:15.
                    </simple> at 119:15.
                  </expr> at 119:15.
                  <statements> at 119:17.
                    <statement> at 119:17.
                      <output> at 119:17.
                      </output> at 120:3.
                    </statement> at 120:3.
                  </statements> at 120:3.
                  </elif> at 120:3.
                  <elif> at 120:3.
                  <expr> at 120:8.
                    <simple> at 120:8.
                      <term> at 120:8.
                        <factor> at 120:8.
                        </factor> at 120:10.
                      </term> at 120:10.
                    </simple> at 120:10.
                    <simple> at 120:12.
                      <term> at 120:12.
                        <factor> at 120:12.
                        </factor> at 120:15.
                      </term> at 120:15.
                    </simple> at 120:15.
                  </expr> at 120:15.
                  <statements> at 120:17.
                    <statement> at 120:17.
                      <output> at 120:17.
                      </output> at 121:3.
                    </statement> at 121:3.
                  </statements> at 121:3.
                  </elif> at 121:3.
                  <elif> at 121:3.
                  <expr> at 121:8.
                    <simple> at 121:8.
                      <term> at 121:8.
                        <factor> at 121:8.
                        </factor> at 121:10.
                      </term> at 121:10.
                    </simple> at 121:10.
                    <simple> at 121:12.
                      <term> at 121:12.
                        <factor> at 121:12.
                        </factor> at 121:15.
                      </term> at 121:15.
                    </simple> at 121:15.
                  </expr> at 121:15.
                  <statements> at 121:17.
                    <statement> at 121:17.
                      <output> at 121:17.
                      </output> at 122:3.
                    </statement> at 122:3.
                  </statements> at 122:3.
                  </elif> at 122:3.
                  <elif> at 122:3.
                  <expr> at 122:8.
                    <simple> at 122:8.
                      <term> at 122:8.
                        <factor> at 122:8.
                        </factor> at 122:10.
                      </term> at 122:10.
                    </simple> at 122:10.
                    <simple> at 122:12.
                      <term> at 122:12.
                        <factor> at 122:12.
                        </factor> at 122:15.
                      </term> at 122:15.
                    </simple> at 122:15.
                  </expr> at 122:15.
                  <statements> at 122:17.
                    <statement> at 122:17.
                      <output> at 122:17.
                      </output> at 123:3.
                    </statement> at 123:3.
                  </statements> at 123:3.
                  </elif> at 123:3.
                  <elif> at 123:3.
                  <expr> at 123:8.
                    <simple> at 123:8.
                      <term> at 123:8.
                        <factor> at 123:8.
                        </factor> at 123:10.
                      </term> at 123:10.
                    </simple> at 123:10.
                    <simple> at 123:12.
                      <term> at 123:12.
                        <factor> at 123:12.
                        </factor> at 123:15.
                      </term> at 123:15.
                    </simple> at 123:15.
                  </expr> at 123:15.
                  <statements> at 123:17.
                    <statement> at 123:17.
                      <output> at 123:17.
                      </output> at 124:3.
                    </statement> at 124:3.
                  </statements> at 124:3.
                  </elif> at 124:3.
                  <elif> at 124:3.
                  <expr> at 124:8.
                    <simple> at 124:8.
                      <term> at 124:8.
                        <factor> at 124:8.
                        </factor> at 124:10.
                      </term> at 124:10.
                    </simple> at 124:10.
                    <simple> at 124:12.
                      <term> at 124:12.
                        <factor> at 124:12.
                        </factor> at 124:15.
                      </term> at 124:15.
                    </simple> at 124:15.
                  </expr> at 124:15.
                  <statements> at 124:17.
                    <statement> at 124:17.
                      <output> at 124:17.
                      </output> at 125:3.
                    </statement> at 125:3.
                  </statements> at 125:3.
                  </elif> at 125:3.
                  <elif> at 125:3.
                  <expr> at 125:8.
                    <simple> at 125:8.
                      <term> at 125:8.
                        <factor> at 125:8.
                        </factor> at 125:10.
                      </term> at 125:10.
                    </simple> at 125:10.
                    <simple> at 125:12.
                      <term> at 125:12.
                        <factor> at 125:12.
                        </factor> at 125:15.
                      </term> at 125:15.
                    </simple> at 125:15.
                  </expr> at 125:15.
                  <statements> at 125:17.
                    <statement> at 125:17.
                      <output> at 125:17.
                      </output> at 126:3.
                    </statement> at 126:3.
                  </statements> at 126:3.
                  </elif> at 126:3.
                  <elif> at 126:3.
                  <expr> at 126:8.
                    <simple> at 126:8.
                      <term> at 126:8.
                        <factor> at 126:8.
                        </factor> at 126:10.
                      </term> at 126:10.
                    </simple> at 126:10.
                    <simple> at 126:12.
                      <term> at 126:12.
                        <factor> at 126:12.
                        </factor> at 126:15.
                      </term> at 126:15.
                    </simple> at 126:15.
                  </expr> at 126:15.
                  <statements> at 126:17.
                    <statement> at 126:17.
                      <output> at 126:17.
                      </output> at 127:3.
                    </statement> at 127:3.
                  </statements> at 127:3.
                  </elif> at 127:3.
                  <elif> at 127:3.
                  <expr> at 127:8.
                    <simple> at 127:8.
                      <term> at 127:8.
                        <factor> at 127:8.
                        </factor> at 127:10.
                      </term> at 127:10.
                    </simple> at 127:10.
                    <simple> at 127:12.
                      <term> at 127:12.
                        <factor> at 127:12.
                        </factor> at 127:15.
                      </term> at 127:15.
                    </simple> at 127:15.
                  </expr> at 127:15.
                  <statements> at 127:17.
                    <statement> at 127:17.
                      <output> at 127:17.
                      </output> at 128:3.
                    </statement> at 128:3.
                  </statements> at 128:3.
                  </elif> at 128:3.
                  <elif> at 128:3.
                  <expr> at 128:8.
                    <simple> at 128:8.
                      <term> at 128:8.
                        <factor> at 128:8.
                        </factor> at 128:10.
                      </term> at 128:10.
                    </simple> at 128:10.
                    <simple> at 128:12.
                      <term> at 128:12.
                        <factor> at 128:12.
                        </factor> at 128:15.
                      </term> at 128:15.
                    </simple> at 128:15.
                  </expr> at 128:15.
                  <statements> at 128:17.
                    <statement> at 128:17.
                      <output> at 128:17.
                      </output> at 129:3.
                    </statement> at 129:3.
                  </statements> at 129:3.
                  </elif> at 129:3.
                  <elif> at 129:3.
                  <expr> at 129:8.
                    <simple> at 129:8.
                      <term> at 129:8.
                        <factor> at 129:8.
                        </factor> at 129:10.
                      </term> at 129:10.
                    </simple> at 129:10.
                    <simple> at 129:12.
                      <term> at 129:12.
                        <factor> at 129:12.
                        </factor> at 129:15.
                      </term> at 129:15.
                    </simple> at 129:15.
                  </expr> at 129:15.
                  <statements> at 129:17.
                    <statement> at 129:17.
                      <output> at 129:17.
                      </output> at 130:3.
                    </statement> at 130:3.
                  </statements> at 130:3.
                  </elif> at 130:3.
                  <elif> at 130:3.
                  <expr> at 130:8.
                    <simple> at 130:8.
                      <term> at 130:8.
                        <factor> at 130:8.
                        </factor> at 130:10.
                      </term> at 130:10.
                    </simple> at 130:10.
                    <simple> at 130:12.
                      <term> at 130:12.
                        <factor> at 130:12.
                        </factor> at 130:15.
                      </term> at 130:15.
                    </simple> at 130:15.
                  </expr> at 130:15.
                  <statements> at 130:17.
                    <statement> at 130:17.
                      <output> at 130:17.
                      </output> at 131:3.
                    </statement> at 131:3.
                  </statements> at 131:3.
                  </elif> at 131:3.
                  <elif> at 131:3.
                  <expr> at 131:8.
                    <simple> at 131:8.
                      <term> at 131:8.
                        <factor> at 131:8.
                        </factor> at 131:10.
                      </term> at 131:10.
                    </simple> at 131:10.
                    <simple> at 131:12.
                      <term> at 131:12.
                        <factor> at 131:12.
                        </factor> at 131:15.
                      </term> at 131:15.
                    </simple> at 131:15.
                  </expr> at 131:15.
                  <statements> at 131:17.
                    <statement> at 131:17.
                      <output> at 131:17.
                      </output> at 132:3.
                    </statement> at 132:3.
                  </statements> at 132:3.
                  </elif> at 132:3.
                  <elif> at 132:3.
                  <expr> at 132:8.
                    <simple> at 132:8.
                      <term> at 132:8.
                        <factor> at 132:8.
                        </factor> at 132:10.
                      </term> at 132:10.
                    </simple> at 132:10.
                    <simple> at 132:12.
                      <term> at 132:12.
                        <factor> at 132:12.
                        </factor> at 132:15.
                      </term> at 132:15.
                    </simple> at 132:15.
                  </expr> at 132:15.
                  <statements> at 132:17.
                    <statement> at 132:17.
                      <output> at 132:17.
                      </output> at 133:3.
                    </statement> at 133:3.
                  </statements> at 133:3.
                  </elif> at 133:3.
                  <elif> at 133:3.
                  <expr> at 133:8.
                    <simple> at 133:8.
                      <term> at 133:8.
                        <factor> at 133:8.
                        </factor> at 133:10.
                      </term> at 133:10.
                    </simple> at 133:10.
                    <simple> at 133:12.
                      <term> at 133:12.
                        <factor> at 133:12.
                        </factor> at 133:15.
                      </term> at 133:15.
                    </simple> at 133:15.
                  </expr> at 133:15.
                  <statements> at 133:17.
                    <statement> at 133:17.
                      <output> at 133:17.
                      </output> at 134:3.
                    </statement> at 134:3.
                  </statements> at 134:3.
                  </elif> at 134:3.
                  <elif> at 134:3.
                  <expr> at 134:8.
                    <simple> at 134:8.
                      <term> at 134:8.
                        <factor> at 134:8.
                        </factor> at 134:10.
                      </term> at 134:10.
                    </simple> at 134:10.
                    <simple> at 134:12.
                      <term> at 134:12.
                        <factor> at 134:12.
                        </factor> at 134:15.
                      </term> at 134:15.
                    </simple> at 134:15.
                  </expr> at 134:15.
                  <statements> at 134:17.
                    <statement> at 134:17.
                      <output> at 134:17.
                      </output> at 135:3.
                    </statement> at 135:3.
                  </statements> at 135:3.
                  </elif> at 135:3.
                  <elif> at 135:3.
                  <expr> at 135:8.
                    <simple> at 135:8.
                      <term> at 135:8.
                        <factor> at 135:8.
                        </factor> at 135:10.
                      </term> at 135:10.
                    </simple> at 135:10.
                    <simple> at 135:12.
                      <term> at 135:12.
                        <factor> at 135:12.
                        </factor> at 135:15.
                      </term> at 135:15.
                    </simple> at 135:15.
                  </expr> at 135:15.
                  <statements> at 135:17.
                    <statement> at 135:17.
                      <output> at 135:17.
                      </output> at 136:3.
                    </statement> at 136:3.
                  </statements> at 136:3.
                  </elif> at 136:3.
                  <elif> at 136:3.
                  <expr> at 136:8.
                    <simple> at 136:8.
                      <term> at 136:8.
                        <factor> at 136:8.
                        </factor> at 136:10.
                      </term> at 136:10.
                    </simple> at 136:10.
                    <simple> at 136:12.
                      <term> at 136:12.
                        <factor> at 136:12.
                        </factor> at 136:15.
                      </term> at 136:15.
                    </simple> at 136:15.
                  </expr> at 136:15.
                  <statements> at 136:17.
                    <statement> at 136:17.
                      <output> at 136:17.
                      </output> at 137:3.
                    </statement> at 137:3.
                  </statements> at 137:3.
                  </elif> at 137:3.
                  <else> at 137:3.
                  <statements> at 137:9.
                  </statements> at 138:3.
                  </else> at 138:3.
                </if> at 138:6.
              </statement> at 138:6.
              <statement> at 139:3.
                <assign> at 139:3.
                  <expr> at 139:11.
                    <simple> at 139:11.
                      <term> at 139:11.
                        <factor> at 139:11.
                        </factor> at 139:13.
                      </term> at 139:13.
                      <term> at 139:15.
                        <factor> at 139:15.
                        </factor> at 140:2.
                      </term> at 140:2.
                    </simple> at 140:2.
                  </expr> at 140:2.
                </assign> at 140:2.
              </statement> at 140:2.
            </statements> at 140:2.
          </while> at 142:1.
        </statement> at 142:1.
      </statements> at 142:1.
    </body> at 142:1.
  </subdef> at 142:1.
  <body> at 143:2.
    <vardef> at 143:2.
      <type> at 143:2.
      </type> at 143:12.
    </vardef> at 144:2.
    <vardef> at 144:2.
      <type> at 144:2.
      </type> at 144:6.
    </vardef> at 146:2.
    <statements> at 146:2.
      <statement> at 146:2.
        <output> at 146:2.
        </output> at 146:63.
      </statement> at 146:63.
      <statement> at 147:2.
        <assign> at 147:2.
          <simple> at 147:16.
            <term> at 147:16.
              <factor> at 147:16.
              </factor> at 147:21.
            </term> at 147:21.
          </simple> at 147:21.
        </assign> at 147:21.
      </statement> at 147:21.
      <statement> at 148:2.
        <output> at 148:2.
        </output> at 148:97.
      </statement> at 148:97.
      <statement> at 149:2.
        <assign> at 149:2.
          <expr> at 149:10.
            <simple> at 149:10.
              <term> at 149:10.
                <factor> at 149:10.
                </factor> at 149:11.
              </term> at 149:11.
            </simple> at 149:11.
          </expr> at 149:11.
        </assign> at 149:11.
      </statement> at 149:11.
      <statement> at 150:2.
        <assign> at 150:2.
          <expr> at 150:10.
            <simple> at 150:10.
              <term> at 150:11.
                <factor> at 150:11.
                </factor> at 150:12.
              </term> at 150:12.
            </simple> at 150:12.
          </expr> at 150:12.
        </assign> at 150:12.
      </statement> at 150:12.
      <statement> at 151:2.
        <while> at 151:2.
          <expr> at 151:8.
            <simple> at 151:8.
              <term> at 151:8.
                <factor> at 151:8.
                  <expr> at 151:9.
                    <simple> at 151:9.
                      <term> at 151:9.
                        <factor> at 151:9.
                        </factor> at 151:11.
                      </term> at 151:11.
                    </simple> at 151:11.
                    <simple> at 151:14.
                      <term> at 151:14.
                        <factor> at 151:14.
                        </factor> at 151:15.
                      </term> at 151:15.
                    </simple> at 151:15.
                  </expr> at 151:15.
                </factor> at 151:17.
                <factor> at 151:21.
                  <expr> at 151:22.
                    <simple> at 151:22.
                      <term> at 151:22.
                        <factor> at 151:22.
                        </factor> at 151:24.
                      </term> at 151:24.
                    </simple> at 151:24.
                    <simple> at 151:26.
                      <term> at 151:26.
                        <factor> at 151:26.
                        </factor> at 151:31.
                      </term> at 151:31.
                    </simple> at 151:31.
                  </expr> at 151:31.
                </factor> at 151:32.
              </term> at 151:32.
            </simple> at 151:32.
          </expr> at 151:32.
          <statements> at 152:3.
            <statement> at 152:3.
              <input> at 152:3.
              </input> at 152:12.
            </statement> at 152:12.
            <statement> at 153:3.
              <assign> at 153:3.
                <index> at 153:8.
                  <simple> at 153:9.
                    <term> at 153:9.
                      <factor> at 153:9.
                      </factor> at 153:10.
                    </term> at 153:10.
                  </simple> at 153:10.
                </index> at 153:12.
                <expr> at 153:14.
                  <simple> at 153:14.
                    <term> at 153:14.
                      <factor> at 153:14.
                      </factor> at 153:15.
                    </term> at 153:15.
                  </simple> at 153:15.
                </expr> at 153:15.
              </assign> at 153:15.
            </statement> at 153:15.
            <statement> at 154:3.
              <assign> at 154:3.
                <expr> at 154:11.
                  <simple> at 154:11.
                    <term> at 154:11.
                      <factor> at 154:11.
                      </factor> at 154:13.
                    </term> at 154:13.
                    <term> at 154:15.
                      <factor> at 154:15.
                      </factor> at 155:2.
                    </term> at 155:2.
                  </simple> at 155:2.
                </expr> at 155:2.
              </assign> at 155:2.
            </statement> at 155:2.
          </statements> at 155:2.
        </while> at 155:5.
      </statement> at 155:5.
      <statement> at 156:2.
        <output> at 156:2.
        </output> at 156:14.
      </statement> at 156:14.
      <statement> at 157:2.
        <call> at 157:2.
          <arglist> at 157:7.
            <expr> at 157:8.
              <simple> at 157:8.
                <term> at 157:8.
                  <factor> at 157:8.
                  </factor> at 157:9.
                </term> at 157:9.
              </simple> at 157:9.
            </expr> at 157:9.
          </arglist> at 157:10.
        </call> at 157:10.
      </statement> at 157:10.
      <statement> at 158:2.
        <output> at 158:2.
        </output> at 158:18.
      </statement> at 158:18.
      <statement> at 159:2.
        <assign> at 159:2.
          <simple> at 159:16.
            <term> at 159:16.
              <factor> at 159:16.
              </factor> at 159:21.
            </term> at 159:21.
          </simple> at 159:21.
        </assign> at 159:21.
      </statement> at 159:21.
      <statement> at 160:2.
        <output> at 160:2.
        </output> at 160:97.
      </statement> at 160:97.
      <statement> at 161:2.
        <assign> at 161:2.
          <expr> at 161:10.
            <simple> at 161:10.
              <term> at 161:10.
                <factor> at 161:10.
                </factor> at 161:11.
              </term> at 161:11.
            </simple> at 161:11.
          </expr> at 161:11.
        </assign> at 161:11.
      </statement> at 161:11.
      <statement> at 162:2.
        <assign> at 162:2.
          <expr> at 162:10.
            <simple> at 162:10.
              <term> at 162:11.
                <factor> at 162:11.
                </factor> at 162:12.
              </term> at 162:12.
            </simple> at 162:12.
          </expr> at 162:12.
        </assign> at 162:12.
      </statement> at 162:12.
      <statement> at 163:2.
        <while> at 163:2.
          <expr> at 163:8.
            <simple> at 163:8.
              <term> at 163:8.
                <factor> at 163:8.
                  <expr> at 163:9.
                    <simple> at 163:9.
                      <term> at 163:9.
                        <factor> at 163:9.
                        </factor> at 163:11.
                      </term> at 163:11.
                    </simple> at 163:11.
                    <simple> at 163:14.
                      <term> at 163:14.
                        <factor> at 163:14.
                        </factor> at 163:15.
                      </term> at 163:15.
                    </simple> at 163:15.
                  </expr> at 163:15.
                </factor> at 163:17.
                <factor> at 163:21.
                  <expr> at 163:22.
                    <simple> at 163:22.
                      <term> at 163:22.
                        <factor> at 163:22.
                        </factor> at 163:24.
                      </term> at 163:24.
                    </simple> at 163:24.
                    <simple> at 163:26.
                      <term> at 163:26.
                        <factor> at 163:26.
                        </factor> at 163:31.
                      </term> at 163:31.
                    </simple> at 163:31.
                  </expr> at 163:31.
                </factor> at 163:32.
              </term> at 163:32.
            </simple> at 163:32.
          </expr> at 163:32.
          <statements> at 164:3.
            <statement> at 164:3.
              <input> at 164:3.
              </input> at 164:12.
            </statement> at 164:12.
            <statement> at 165:3.
              <assign> at 165:3.
                <index> at 165:8.
                  <simple> at 165:9.
                    <term> at 165:9.
                      <factor> at 165:9.
                      </factor> at 165:10.
                    </term> at 165:10.
                  </simple> at 165:10.
                </index> at 165:12.
                <expr> at 165:14.
                  <simple> at 165:14.
                    <term> at 165:14.
                      <factor> at 165:14.
                      </factor> at 165:15.
                    </term> at 165:15.
                  </simple> at 165:15.
                </expr> at 165:15.
              </assign> at 165:15.
            </statement> at 165:15.
            <statement> at 166:3.
              <assign> at 166:3.
                <expr> at 166:11.
                  <simple> at 166:11.
                    <term> at 166:11.
                      <factor> at 166:11.
                      </factor> at 166:13.
                    </term> at 166:13.
                    <term> at 166:15.
                      <factor> at 166:15.
                      </factor> at 167:2.
                    </term> at 167:2.
                  </simple> at 167:2.
                </expr> at 167:2.
              </assign> at 167:2.
            </statement> at 167:2.
          </statements> at 167:2.
        </while> at 167:5.
      </statement> at 167:5.
      <statement> at 168:2.
        <output> at 168:2.
        </output> at 168:14.
      </statement> at 168:14.
      <statement> at 169:2.
        <call> at 169:2.
          <arglist> at 169:7.
            <expr> at 169:8.
              <simple> at 169:8.
                <term> at 169:8.
                  <factor> at 169:8.
                  </factor> at 169:9.
                </term> at 169:9.
              </simple> at 169:9.
            </expr> at 169:9.
          </arglist> at 169:10.
        </call> at 169:10.
      </statement> at 169:10.
      <statement> at 170:2.
        <output> at 170:2.
        </output> at 170:18.
      </statement> at 170:18.
      <statement> at 171:2.
        <output> at 171:2.
        </output> at 171:25.
      </statement> at 171:25.
      <statement> at 172:2.
        <assign> at 172:2.
          <expr> at 172:10.
            <simple> at 172:10.
              <term> at 172:10.
                <factor> at 172:10.
                  <arglist> at 172:14.
                    <expr> at 172:15.
                      <simple> at 172:15.
                        <term> at 172:15.
                          <factor> at 172:15.
                          </factor> at 172:16.
                        </term> at 172:16.
                      </simple> at 172:16.
                    </expr> at 172:16.
                    <expr> at 172:18.
                      <simple> at 172:18.
                        <term> at 172:18.
                          <factor> at 172:18.
                          </factor> at 172:19.
                        </term> at 172:19.
                      </simple> at 172:19.
                    </expr> at 172:19.
                  </arglist> at 172:20.
                </factor> at 172:20.
              </term> at 172:20.
            </simple> at 172:20.
          </expr> at 172:20.
        </assign> at 172:20.
      </statement> at 172:20.
      <statement> at 173:2.
        <call> at 173:2.
          <arglist> at 173:7.
            <expr> at 173:8.
              <simple> at 173:8.
                <term> at 173:8.
                  <factor> at 173:8.
                  </factor> at 173:9.
                </term> at 173:9.
              </simple> at 173:9.
            </expr> at 173:9.
          </arglist> at 173:10.
        </call> at 173:10.
      </statement> at 173:10.
      <statement> at 174:2.
        <output> at 174:2.
        </output> at 174:15.
      </statement> at 174:15.
    </statements> at 174:15.
  </body> at 174:15.
</program> at 174:15.
Generated: test38.class
.class public test38
.super java/lang/Object

.field private static final charsetName Ljava/lang/String;
.field private static final usLocale Ljava/util/Locale;
.field private static final scanner Ljava/util/Scanner;

.method static public <clinit>()V
.limit stack 5
.limit locals 1 
	ldc	"UTF-8"
	putstatic test38/charsetName Ljava/lang/String;
	new	java/util/Locale
	dup
	ldc	"en"
	ldc	"US"
	invokespecial java/util/Locale/<init>(Ljava/lang/String;Ljava/lang/String;)V
	putstatic test38/usLocale Ljava/util/Locale;
	new	java/util/Scanner
	dup
	new	java/io/BufferedInputStream
	dup
	getstatic java/lang/System/in Ljava/io/InputStream;
	invokespecial java/io/BufferedInputStream/<init>(Ljava/io/InputStream;)V
	getstatic test38/charsetName Ljava/lang/String;
	invokespecial java/util/Scanner/<init>(Ljava/io/InputStream;Ljava/lang/String;)V
	putstatic test38/scanner Ljava/util/Scanner;
	getstatic test38/scanner Ljava/util/Scanner;
	getstatic test38/usLocale Ljava/util/Locale;
	invokevirtual java/util/Scanner/useLocale(Ljava/util/Locale;)Ljava/util/Scanner;
	pop
	return
.end method

.method public <init>()V
	aload_0
	invokespecial java/lang/Object/<init>()V
	return
.end method

.method public static readInt()I
.limit stack 1
.limit locals 1
	getstatic test38/scanner Ljava/util/Scanner;
	invokevirtual java/util/Scanner/nextInt()I
	ireturn
.end method

.method public static readBoolean()Z
.limit stack 2
.limit locals 1
	getstatic test38/scanner Ljava/util/Scanner;
	invokevirtual java/util/Scanner/next()Ljava/lang/String;
	astore 0
	aload 0
	ldc	"true"
	invokevirtual java/lang/String/equalsIgnoreCase(Ljava/lang/String;)Z
	ifeq False
	iconst_1
	ireturn
False:
	aload 0
	ldc	"false"
	invokevirtual java/lang/String/equalsIgnoreCase(Ljava/lang/String;)Z
	ifeq Exception
	iconst_0
	ireturn
Exception:
	new	java/util/InputMismatchException
	dup
	invokespecial java/util/InputMismatchException/<init>()V
	athrow
.end method

.method public static main([Ljava/lang/String;)V
.limit stack 30
.limit locals 6
	getstatic java/lang/System/out Ljava/io/PrintStream;
	ldc "Join the following strings:\n(with int arrays!)\n\n"
	invokevirtual java/io/PrintStream/print(Ljava/lang/String;)V
	ldc 50000
	newarray int
	astore 1
	getstatic java/lang/System/out Ljava/io/PrintStream;
	ldc "Please enter the ascii values for string 1:\nUse a 0 to mark the end of the string.\n"
	invokevirtual java/io/PrintStream/print(Ljava/lang/String;)V
	ldc 0
	istore 4
	ldc 1
	ineg
	istore 5
L312:
	iload 5
	ldc 0
	if_icmpne L314
	ldc 0
	goto L315
L314:
	ldc 1
L315:
	iload 4
	ldc 50000
	if_icmplt L316
	ldc 0
	goto L317
L316:
	ldc 1
L317:
	iand
	ifeq L313
	invokestatic test38/readInt()I
	istore 5
	aload 1
	iload 4
	iload 5
	iastore
	iload 4
	ldc 1
	iadd
	istore 4
	goto L312
L313:
	getstatic java/lang/System/out Ljava/io/PrintStream;
	ldc "\""
	invokevirtual java/io/PrintStream/print(Ljava/lang/String;)V
	aload 1
	invokestatic test38.print([I)V
	getstatic java/lang/System/out Ljava/io/PrintStream;
	ldc "\"\n\n"
	invokevirtual java/io/PrintStream/print(Ljava/lang/String;)V
	ldc 50000
	newarray int
	astore 2
	getstatic java/lang/System/out Ljava/io/PrintStream;
	ldc "Please enter the ascii values for string 2:\nUse a 0 to mark the end of the string.\n"
	invokevirtual java/io/PrintStream/print(Ljava/lang/String;)V
	ldc 0
	istore 4
	ldc 1
	ineg
	istore 5
L318:
	iload 5
	ldc 0
	if_icmpne L320
	ldc 0
	goto L321
L320:
	ldc 1
L321:
	iload 4
	ldc 50000
	if_icmplt L322
	ldc 0
	goto L323
L322:
	ldc 1
L323:
	iand
	ifeq L319
	invokestatic test38/readInt()I
	istore 5
	aload 2
	iload 4
	iload 5
	iastore
	iload 4
	ldc 1
	iadd
	istore 4
	goto L318
L319:
	getstatic java/lang/System/out Ljava/io/PrintStream;
	ldc "\""
	invokevirtual java/io/PrintStream/print(Ljava/lang/String;)V
	aload 2
	invokestatic test38.print([I)V
	getstatic java/lang/System/out Ljava/io/PrintStream;
	ldc "\"\n\n"
	invokevirtual java/io/PrintStream/print(Ljava/lang/String;)V
	getstatic java/lang/System/out Ljava/io/PrintStream;
	ldc "\nRESULT:\n\""
	invokevirtual java/io/PrintStream/print(Ljava/lang/String;)V
	aload 1
	aload 2
	invokestatic test38.join([I[I)[I
	astore 3
	aload 3
	invokestatic test38.print([I)V
	getstatic java/lang/System/out Ljava/io/PrintStream;
	ldc "\"\n"
	invokevirtual java/io/PrintStream/print(Ljava/lang/String;)V
	return
.end method

.method public static print([I)V
.limit stack 298
.limit locals 3
	ldc 0
	istore 1
L13:
	aload 0
	iload 1
	iaload
	ldc 0
	if_icmpne L15
	ldc 0
	goto L16
L15:
	ldc 1
L16:
	ifeq L14
	aload 0
	iload 1
	iaload
	istore 2
	iload 2
	ldc 9
	if_icmpeq L19
	ldc 0
	goto L20
L19:
	ldc 1
L20:
	ifeq L18
	getstatic java/lang/System/out Ljava/io/PrintStream;
	ldc "\t"
	invokevirtual java/io/PrintStream/print(Ljava/lang/String;)V
	goto L17
L18:
	iload 2
	ldc 10
	if_icmpeq L22
	ldc 0
	goto L23
L22:
	ldc 1
L23:
	ifeq L21
	getstatic java/lang/System/out Ljava/io/PrintStream;
	ldc "\n"
	invokevirtual java/io/PrintStream/print(Ljava/lang/String;)V
	goto L17
L21:
	iload 2
	ldc 32
	if_icmpeq L25
	ldc 0
	goto L26
L25:
	ldc 1
L26:
	ifeq L24
	getstatic java/lang/System/out Ljava/io/PrintStream;
	ldc " "
	invokevirtual java/io/PrintStream/print(Ljava/lang/String;)V
	goto L17
L24:
	iload 2
	ldc 33
	if_icmpeq L28
	ldc 0
	goto L29
L28:
	ldc 1
L29:
	ifeq L27
	getstatic java/lang/System/out Ljava/io/PrintStream;
	ldc "!"
	invokevirtual java/io/PrintStream/print(Ljava/lang/String;)V
	goto L17
L27:
	iload 2
	ldc 34
	if_icmpeq L31
	ldc 0
	goto L32
L31:
	ldc 1
L32:
	ifeq L30
	getstatic java/lang/System/out Ljava/io/PrintStream;
	ldc "\""
	invokevirtual java/io/PrintStream/print(Ljava/lang/String;)V
	goto L17
L30:
	iload 2
	ldc 35
	if_icmpeq L34
	ldc 0
	goto L35
L34:
	ldc 1
L35:
	ifeq L33
	getstatic java/lang/System/out Ljava/io/PrintStream;
	ldc "\n"
	invokevirtual java/io/PrintStream/print(Ljava/lang/String;)V
	goto L17
L33:
	iload 2
	ldc 35
	if_icmpeq L37
	ldc 0
	goto L38
L37:
	ldc 1
L38:
	ifeq L36
	getstatic java/lang/System/out Ljava/io/PrintStream;
	ldc "#"
	invokevirtual java/io/PrintStream/print(Ljava/lang/String;)V
	goto L17
L36:
	iload 2
	ldc 36
	if_icmpeq L40
	ldc 0
	goto L41
L40:
	ldc 1
L41:
	ifeq L39
	getstatic java/lang/System/out Ljava/io/PrintStream;
	ldc "$"
	invokevirtual java/io/PrintStream/print(Ljava/lang/String;)V
	goto L17
L39:
	iload 2
	ldc 37
	if_icmpeq L43
	ldc 0
	goto L44
L43:
	ldc 1
L44:
	ifeq L42
	getstatic java/lang/System/out Ljava/io/PrintStream;
	ldc "%"
	invokevirtual java/io/PrintStream/print(Ljava/lang/String;)V
	goto L17
L42:
	iload 2
	ldc 38
	if_icmpeq L46
	ldc 0
	goto L47
L46:
	ldc 1
L47:
	ifeq L45
	getstatic java/lang/System/out Ljava/io/PrintStream;
	ldc "&"
	invokevirtual java/io/PrintStream/print(Ljava/lang/String;)V
	goto L17
L45:
	iload 2
	ldc 39
	if_icmpeq L49
	ldc 0
	goto L50
L49:
	ldc 1
L50:
	ifeq L48
	getstatic java/lang/System/out Ljava/io/PrintStream;
	ldc "'"
	invokevirtual java/io/PrintStream/print(Ljava/lang/String;)V
	goto L17
L48:
	iload 2
	ldc 40
	if_icmpeq L52
	ldc 0
	goto L53
L52:
	ldc 1
L53:
	ifeq L51
	getstatic java/lang/System/out Ljava/io/PrintStream;
	ldc "("
	invokevirtual java/io/PrintStream/print(Ljava/lang/String;)V
	goto L17
L51:
	iload 2
	ldc 41
	if_icmpeq L55
	ldc 0
	goto L56
L55:
	ldc 1
L56:
	ifeq L54
	getstatic java/lang/System/out Ljava/io/PrintStream;
	ldc ")"
	invokevirtual java/io/PrintStream/print(Ljava/lang/String;)V
	goto L17
L54:
	iload 2
	ldc 42
	if_icmpeq L58
	ldc 0
	goto L59
L58:
	ldc 1
L59:
	ifeq L57
	getstatic java/lang/System/out Ljava/io/PrintStream;
	ldc "*"
	invokevirtual java/io/PrintStream/print(Ljava/lang/String;)V
	goto L17
L57:
	iload 2
	ldc 43
	if_icmpeq L61
	ldc 0
	goto L62
L61:
	ldc 1
L62:
	ifeq L60
	getstatic java/lang/System/out Ljava/io/PrintStream;
	ldc "+"
	invokevirtual java/io/PrintStream/print(Ljava/lang/String;)V
	goto L17
L60:
	iload 2
	ldc 44
	if_icmpeq L64
	ldc 0
	goto L65
L64:
	ldc 1
L65:
	ifeq L63
	getstatic java/lang/System/out Ljava/io/PrintStream;
	ldc ","
	invokevirtual java/io/PrintStream/print(Ljava/lang/String;)V
	goto L17
L63:
	iload 2
	ldc 45
	if_icmpeq L67
	ldc 0
	goto L68
L67:
	ldc 1
L68:
	ifeq L66
	getstatic java/lang/System/out Ljava/io/PrintStream;
	ldc "-"
	invokevirtual java/io/PrintStream/print(Ljava/lang/String;)V
	goto L17
L66:
	iload 2
	ldc 46
	if_icmpeq L70
	ldc 0
	goto L71
L70:
	ldc 1
L71:
	ifeq L69
	getstatic java/lang/System/out Ljava/io/PrintStream;
	ldc "."
	invokevirtual java/io/PrintStream/print(Ljava/lang/String;)V
	goto L17
L69:
	iload 2
	ldc 47
	if_icmpeq L73
	ldc 0
	goto L74
L73:
	ldc 1
L74:
	ifeq L72
	getstatic java/lang/System/out Ljava/io/PrintStream;
	ldc "/"
	invokevirtual java/io/PrintStream/print(Ljava/lang/String;)V
	goto L17
L72:
	iload 2
	ldc 48
	if_icmpeq L76
	ldc 0
	goto L77
L76:
	ldc 1
L77:
	ifeq L75
	getstatic java/lang/System/out Ljava/io/PrintStream;
	ldc "0"
	invokevirtual java/io/PrintStream/print(Ljava/lang/String;)V
	goto L17
L75:
	iload 2
	ldc 49
	if_icmpeq L79
	ldc 0
	goto L80
L79:
	ldc 1
L80:
	ifeq L78
	getstatic java/lang/System/out Ljava/io/PrintStream;
	ldc "1"
	invokevirtual java/io/PrintStream/print(Ljava/lang/String;)V
	goto L17
L78:
	iload 2
	ldc 50
	if_icmpeq L82
	ldc 0
	goto L83
L82:
	ldc 1
L83:
	ifeq L81
	getstatic java/lang/System/out Ljava/io/PrintStream;
	ldc "2"
	invokevirtual java/io/PrintStream/print(Ljava/lang/String;)V
	goto L17
L81:
	iload 2
	ldc 51
	if_icmpeq L85
	ldc 0
	goto L86
L85:
	ldc 1
L86:
	ifeq L84
	getstatic java/lang/System/out Ljava/io/PrintStream;
	ldc "3"
	invokevirtual java/io/PrintStream/print(Ljava/lang/String;)V
	goto L17
L84:
	iload 2
	ldc 52
	if_icmpeq L88
	ldc 0
	goto L89
L88:
	ldc 1
L89:
	ifeq L87
	getstatic java/lang/System/out Ljava/io/PrintStream;
	ldc "4"
	invokevirtual java/io/PrintStream/print(Ljava/lang/String;)V
	goto L17
L87:
	iload 2
	ldc 53
	if_icmpeq L91
	ldc 0
	goto L92
L91:
	ldc 1
L92:
	ifeq L90
	getstatic java/lang/System/out Ljava/io/PrintStream;
	ldc "5"
	invokevirtual java/io/PrintStream/print(Ljava/lang/String;)V
	goto L17
L90:
	iload 2
	ldc 54
	if_icmpeq L94
	ldc 0
	goto L95
L94:
	ldc 1
L95:
	ifeq L93
	getstatic java/lang/System/out Ljava/io/PrintStream;
	ldc "6"
	invokevirtual java/io/PrintStream/print(Ljava/lang/String;)V
	goto L17
L93:
	iload 2
	ldc 55
	if_icmpeq L97
	ldc 0
	goto L98
L97:
	ldc 1
L98:
	ifeq L96
	getstatic java/lang/System/out Ljava/io/PrintStream;
	ldc "7"
	invokevirtual java/io/PrintStream/print(Ljava/lang/String;)V
	goto L17
L96:
	iload 2
	ldc 56
	if_icmpeq L100
	ldc 0
	goto L101
L100:
	ldc 1
L101:
	ifeq L99
	getstatic java/lang/System/out Ljava/io/PrintStream;
	ldc "8"
	invokevirtual java/io/PrintStream/print(Ljava/lang/String;)V
	goto L17
L99:
	iload 2
	ldc 57
	if_icmpeq L103
	ldc 0
	goto L104
L103:
	ldc 1
L104:
	ifeq L102
	getstatic java/lang/System/out Ljava/io/PrintStream;
	ldc "9"
	invokevirtual java/io/PrintStream/print(Ljava/lang/String;)V
	goto L17
L102:
	iload 2
	ldc 58
	if_icmpeq L106
	ldc 0
	goto L107
L106:
	ldc 1
L107:
	ifeq L105
	getstatic java/lang/System/out Ljava/io/PrintStream;
	ldc ":"
	invokevirtual java/io/PrintStream/print(Ljava/lang/String;)V
	goto L17
L105:
	iload 2
	ldc 59
	if_icmpeq L109
	ldc 0
	goto L110
L109:
	ldc 1
L110:
	ifeq L108
	getstatic java/lang/System/out Ljava/io/PrintStream;
	ldc ";"
	invokevirtual java/io/PrintStream/print(Ljava/lang/String;)V
	goto L17
L108:
	iload 2
	ldc 60
	if_icmpeq L112
	ldc 0
	goto L113
L112:
	ldc 1
L113:
	ifeq L111
	getstatic java/lang/System/out Ljava/io/PrintStream;
	ldc "<"
	invokevirtual java/io/PrintStream/print(Ljava/lang/String;)V
	goto L17
L111:
	iload 2
	ldc 61
	if_icmpeq L115
	ldc 0
	goto L116
L115:
	ldc 1
L116:
	ifeq L114
	getstatic java/lang/System/out Ljava/io/PrintStream;
	ldc "="
	invokevirtual java/io/PrintStream/print(Ljava/lang/String;)V
	goto L17
L114:
	iload 2
	ldc 62
	if_icmpeq L118
	ldc 0
	goto L119
L118:
	ldc 1
L119:
	ifeq L117
	getstatic java/lang/System/out Ljava/io/PrintStream;
	ldc ">"
	invokevirtual java/io/PrintStream/print(Ljava/lang/String;)V
	goto L17
L117:
	iload 2
	ldc 63
	if_icmpeq L121
	ldc 0
	goto L122
L121:
	ldc 1
L122:
	ifeq L120
	getstatic java/lang/System/out Ljava/io/PrintStream;
	ldc "?"
	invokevirtual java/io/PrintStream/print(Ljava/lang/String;)V
	goto L17
L120:
	iload 2
	ldc 64
	if_icmpeq L124
	ldc 0
	goto L125
L124:
	ldc 1
L125:
	ifeq L123
	getstatic java/lang/System/out Ljava/io/PrintStream;
	ldc "@"
	invokevirtual java/io/PrintStream/print(Ljava/lang/String;)V
	goto L17
L123:
	iload 2
	ldc 65
	if_icmpeq L127
	ldc 0
	goto L128
L127:
	ldc 1
L128:
	ifeq L126
	getstatic java/lang/System/out Ljava/io/PrintStream;
	ldc "A"
	invokevirtual java/io/PrintStream/print(Ljava/lang/String;)V
	goto L17
L126:
	iload 2
	ldc 66
	if_icmpeq L130
	ldc 0
	goto L131
L130:
	ldc 1
L131:
	ifeq L129
	getstatic java/lang/System/out Ljava/io/PrintStream;
	ldc "B"
	invokevirtual java/io/PrintStream/print(Ljava/lang/String;)V
	goto L17
L129:
	iload 2
	ldc 67
	if_icmpeq L133
	ldc 0
	goto L134
L133:
	ldc 1
L134:
	ifeq L132
	getstatic java/lang/System/out Ljava/io/PrintStream;
	ldc "C"
	invokevirtual java/io/PrintStream/print(Ljava/lang/String;)V
	goto L17
L132:
	iload 2
	ldc 68
	if_icmpeq L136
	ldc 0
	goto L137
L136:
	ldc 1
L137:
	ifeq L135
	getstatic java/lang/System/out Ljava/io/PrintStream;
	ldc "D"
	invokevirtual java/io/PrintStream/print(Ljava/lang/String;)V
	goto L17
L135:
	iload 2
	ldc 69
	if_icmpeq L139
	ldc 0
	goto L140
L139:
	ldc 1
L140:
	ifeq L138
	getstatic java/lang/System/out Ljava/io/PrintStream;
	ldc "E"
	invokevirtual java/io/PrintStream/print(Ljava/lang/String;)V
	goto L17
L138:
	iload 2
	ldc 70
	if_icmpeq L142
	ldc 0
	goto L143
L142:
	ldc 1
L143:
	ifeq L141
	getstatic java/lang/System/out Ljava/io/PrintStream;
	ldc "F"
	invokevirtual java/io/PrintStream/print(Ljava/lang/String;)V
	goto L17
L141:
	iload 2
	ldc 71
	if_icmpeq L145
	ldc 0
	goto L146
L145:
	ldc 1
L146:
	ifeq L144
	getstatic java/lang/System/out Ljava/io/PrintStream;
	ldc "G"
	invokevirtual java/io/PrintStream/print(Ljava/lang/String;)V
	goto L17
L144:
	iload 2
	ldc 72
	if_icmpeq L148
	ldc 0
	goto L149
L148:
	ldc 1
L149:
	ifeq L147
	getstatic java/lang/System/out Ljava/io/PrintStream;
	ldc "H"
	invokevirtual java/io/PrintStream/print(Ljava/lang/String;)V
	goto L17
L147:
	iload 2
	ldc 73
	if_icmpeq L151
	ldc 0
	goto L152
L151:
	ldc 1
L152:
	ifeq L150
	getstatic java/lang/System/out Ljava/io/PrintStream;
	ldc "I"
	invokevirtual java/io/PrintStream/print(Ljava/lang/String;)V
	goto L17
L150:
	iload 2
	ldc 74
	if_icmpeq L154
	ldc 0
	goto L155
L154:
	ldc 1
L155:
	ifeq L153
	getstatic java/lang/System/out Ljava/io/PrintStream;
	ldc "J"
	invokevirtual java/io/PrintStream/print(Ljava/lang/String;)V
	goto L17
L153:
	iload 2
	ldc 75
	if_icmpeq L157
	ldc 0
	goto L158
L157:
	ldc 1
L158:
	ifeq L156
	getstatic java/lang/System/out Ljava/io/PrintStream;
	ldc "K"
	invokevirtual java/io/PrintStream/print(Ljava/lang/String;)V
	goto L17
L156:
	iload 2
	ldc 76
	if_icmpeq L160
	ldc 0
	goto L161
L160:
	ldc 1
L161:
	ifeq L159
	getstatic java/lang/System/out Ljava/io/PrintStream;
	ldc "L"
	invokevirtual java/io/PrintStream/print(Ljava/lang/String;)V
	goto L17
L159:
	iload 2
	ldc 77
	if_icmpeq L163
	ldc 0
	goto L164
L163:
	ldc 1
L164:
	ifeq L162
	getstatic java/lang/System/out Ljava/io/PrintStream;
	ldc "M"
	invokevirtual java/io/PrintStream/print(Ljava/lang/String;)V
	goto L17
L162:
	iload 2
	ldc 78
	if_icmpeq L166
	ldc 0
	goto L167
L166:
	ldc 1
L167:
	ifeq L165
	getstatic java/lang/System/out Ljava/io/PrintStream;
	ldc "N"
	invokevirtual java/io/PrintStream/print(Ljava/lang/String;)V
	goto L17
L165:
	iload 2
	ldc 79
	if_icmpeq L169
	ldc 0
	goto L170
L169:
	ldc 1
L170:
	ifeq L168
	getstatic java/lang/System/out Ljava/io/PrintStream;
	ldc "O"
	invokevirtual java/io/PrintStream/print(Ljava/lang/String;)V
	goto L17
L168:
	iload 2
	ldc 80
	if_icmpeq L172
	ldc 0
	goto L173
L172:
	ldc 1
L173:
	ifeq L171
	getstatic java/lang/System/out Ljava/io/PrintStream;
	ldc "P"
	invokevirtual java/io/PrintStream/print(Ljava/lang/String;)V
	goto L17
L171:
	iload 2
	ldc 81
	if_icmpeq L175
	ldc 0
	goto L176
L175:
	ldc 1
L176:
	ifeq L174
	getstatic java/lang/System/out Ljava/io/PrintStream;
	ldc "Q"
	invokevirtual java/io/PrintStream/print(Ljava/lang/String;)V
	goto L17
L174:
	iload 2
	ldc 82
	if_icmpeq L178
	ldc 0
	goto L179
L178:
	ldc 1
L179:
	ifeq L177
	getstatic java/lang/System/out Ljava/io/PrintStream;
	ldc "R"
	invokevirtual java/io/PrintStream/print(Ljava/lang/String;)V
	goto L17
L177:
	iload 2
	ldc 83
	if_icmpeq L181
	ldc 0
	goto L182
L181:
	ldc 1
L182:
	ifeq L180
	getstatic java/lang/System/out Ljava/io/PrintStream;
	ldc "S"
	invokevirtual java/io/PrintStream/print(Ljava/lang/String;)V
	goto L17
L180:
	iload 2
	ldc 84
	if_icmpeq L184
	ldc 0
	goto L185
L184:
	ldc 1
L185:
	ifeq L183
	getstatic java/lang/System/out Ljava/io/PrintStream;
	ldc "T"
	invokevirtual java/io/PrintStream/print(Ljava/lang/String;)V
	goto L17
L183:
	iload 2
	ldc 85
	if_icmpeq L187
	ldc 0
	goto L188
L187:
	ldc 1
L188:
	ifeq L186
	getstatic java/lang/System/out Ljava/io/PrintStream;
	ldc "U"
	invokevirtual java/io/PrintStream/print(Ljava/lang/String;)V
	goto L17
L186:
	iload 2
	ldc 86
	if_icmpeq L190
	ldc 0
	goto L191
L190:
	ldc 1
L191:
	ifeq L189
	getstatic java/lang/System/out Ljava/io/PrintStream;
	ldc "V"
	invokevirtual java/io/PrintStream/print(Ljava/lang/String;)V
	goto L17
L189:
	iload 2
	ldc 87
	if_icmpeq L193
	ldc 0
	goto L194
L193:
	ldc 1
L194:
	ifeq L192
	getstatic java/lang/System/out Ljava/io/PrintStream;
	ldc "W"
	invokevirtual java/io/PrintStream/print(Ljava/lang/String;)V
	goto L17
L192:
	iload 2
	ldc 88
	if_icmpeq L196
	ldc 0
	goto L197
L196:
	ldc 1
L197:
	ifeq L195
	getstatic java/lang/System/out Ljava/io/PrintStream;
	ldc "X"
	invokevirtual java/io/PrintStream/print(Ljava/lang/String;)V
	goto L17
L195:
	iload 2
	ldc 89
	if_icmpeq L199
	ldc 0
	goto L200
L199:
	ldc 1
L200:
	ifeq L198
	getstatic java/lang/System/out Ljava/io/PrintStream;
	ldc "Y"
	invokevirtual java/io/PrintStream/print(Ljava/lang/String;)V
	goto L17
L198:
	iload 2
	ldc 90
	if_icmpeq L202
	ldc 0
	goto L203
L202:
	ldc 1
L203:
	ifeq L201
	getstatic java/lang/System/out Ljava/io/PrintStream;
	ldc "Z"
	invokevirtual java/io/PrintStream/print(Ljava/lang/String;)V
	goto L17
L201:
	iload 2
	ldc 91
	if_icmpeq L205
	ldc 0
	goto L206
L205:
	ldc 1
L206:
	ifeq L204
	getstatic java/lang/System/out Ljava/io/PrintStream;
	ldc "["
	invokevirtual java/io/PrintStream/print(Ljava/lang/String;)V
	goto L17
L204:
	iload 2
	ldc 92
	if_icmpeq L208
	ldc 0
	goto L209
L208:
	ldc 1
L209:
	ifeq L207
	getstatic java/lang/System/out Ljava/io/PrintStream;
	ldc "\\"
	invokevirtual java/io/PrintStream/print(Ljava/lang/String;)V
	goto L17
L207:
	iload 2
	ldc 93
	if_icmpeq L211
	ldc 0
	goto L212
L211:
	ldc 1
L212:
	ifeq L210
	getstatic java/lang/System/out Ljava/io/PrintStream;
	ldc "]"
	invokevirtual java/io/PrintStream/print(Ljava/lang/String;)V
	goto L17
L210:
	iload 2
	ldc 94
	if_icmpeq L214
	ldc 0
	goto L215
L214:
	ldc 1
L215:
	ifeq L213
	getstatic java/lang/System/out Ljava/io/PrintStream;
	ldc "^"
	invokevirtual java/io/PrintStream/print(Ljava/lang/String;)V
	goto L17
L213:
	iload 2
	ldc 95
	if_icmpeq L217
	ldc 0
	goto L218
L217:
	ldc 1
L218:
	ifeq L216
	getstatic java/lang/System/out Ljava/io/PrintStream;
	ldc "_"
	invokevirtual java/io/PrintStream/print(Ljava/lang/String;)V
	goto L17
L216:
	iload 2
	ldc 96
	if_icmpeq L220
	ldc 0
	goto L221
L220:
	ldc 1
L221:
	ifeq L219
	getstatic java/lang/System/out Ljava/io/PrintStream;
	ldc "`"
	invokevirtual java/io/PrintStream/print(Ljava/lang/String;)V
	goto L17
L219:
	iload 2
	ldc 97
	if_icmpeq L223
	ldc 0
	goto L224
L223:
	ldc 1
L224:
	ifeq L222
	getstatic java/lang/System/out Ljava/io/PrintStream;
	ldc "a"
	invokevirtual java/io/PrintStream/print(Ljava/lang/String;)V
	goto L17
L222:
	iload 2
	ldc 98
	if_icmpeq L226
	ldc 0
	goto L227
L226:
	ldc 1
L227:
	ifeq L225
	getstatic java/lang/System/out Ljava/io/PrintStream;
	ldc "b"
	invokevirtual java/io/PrintStream/print(Ljava/lang/String;)V
	goto L17
L225:
	iload 2
	ldc 99
	if_icmpeq L229
	ldc 0
	goto L230
L229:
	ldc 1
L230:
	ifeq L228
	getstatic java/lang/System/out Ljava/io/PrintStream;
	ldc "c"
	invokevirtual java/io/PrintStream/print(Ljava/lang/String;)V
	goto L17
L228:
	iload 2
	ldc 100
	if_icmpeq L232
	ldc 0
	goto L233
L232:
	ldc 1
L233:
	ifeq L231
	getstatic java/lang/System/out Ljava/io/PrintStream;
	ldc "d"
	invokevirtual java/io/PrintStream/print(Ljava/lang/String;)V
	goto L17
L231:
	iload 2
	ldc 101
	if_icmpeq L235
	ldc 0
	goto L236
L235:
	ldc 1
L236:
	ifeq L234
	getstatic java/lang/System/out Ljava/io/PrintStream;
	ldc "e"
	invokevirtual java/io/PrintStream/print(Ljava/lang/String;)V
	goto L17
L234:
	iload 2
	ldc 102
	if_icmpeq L238
	ldc 0
	goto L239
L238:
	ldc 1
L239:
	ifeq L237
	getstatic java/lang/System/out Ljava/io/PrintStream;
	ldc "f"
	invokevirtual java/io/PrintStream/print(Ljava/lang/String;)V
	goto L17
L237:
	iload 2
	ldc 103
	if_icmpeq L241
	ldc 0
	goto L242
L241:
	ldc 1
L242:
	ifeq L240
	getstatic java/lang/System/out Ljava/io/PrintStream;
	ldc "g"
	invokevirtual java/io/PrintStream/print(Ljava/lang/String;)V
	goto L17
L240:
	iload 2
	ldc 104
	if_icmpeq L244
	ldc 0
	goto L245
L244:
	ldc 1
L245:
	ifeq L243
	getstatic java/lang/System/out Ljava/io/PrintStream;
	ldc "h"
	invokevirtual java/io/PrintStream/print(Ljava/lang/String;)V
	goto L17
L243:
	iload 2
	ldc 105
	if_icmpeq L247
	ldc 0
	goto L248
L247:
	ldc 1
L248:
	ifeq L246
	getstatic java/lang/System/out Ljava/io/PrintStream;
	ldc "i"
	invokevirtual java/io/PrintStream/print(Ljava/lang/String;)V
	goto L17
L246:
	iload 2
	ldc 106
	if_icmpeq L250
	ldc 0
	goto L251
L250:
	ldc 1
L251:
	ifeq L249
	getstatic java/lang/System/out Ljava/io/PrintStream;
	ldc "j"
	invokevirtual java/io/PrintStream/print(Ljava/lang/String;)V
	goto L17
L249:
	iload 2
	ldc 107
	if_icmpeq L253
	ldc 0
	goto L254
L253:
	ldc 1
L254:
	ifeq L252
	getstatic java/lang/System/out Ljava/io/PrintStream;
	ldc "k"
	invokevirtual java/io/PrintStream/print(Ljava/lang/String;)V
	goto L17
L252:
	iload 2
	ldc 108
	if_icmpeq L256
	ldc 0
	goto L257
L256:
	ldc 1
L257:
	ifeq L255
	getstatic java/lang/System/out Ljava/io/PrintStream;
	ldc "l"
	invokevirtual java/io/PrintStream/print(Ljava/lang/String;)V
	goto L17
L255:
	iload 2
	ldc 109
	if_icmpeq L259
	ldc 0
	goto L260
L259:
	ldc 1
L260:
	ifeq L258
	getstatic java/lang/System/out Ljava/io/PrintStream;
	ldc "m"
	invokevirtual java/io/PrintStream/print(Ljava/lang/String;)V
	goto L17
L258:
	iload 2
	ldc 110
	if_icmpeq L262
	ldc 0
	goto L263
L262:
	ldc 1
L263:
	ifeq L261
	getstatic java/lang/System/out Ljava/io/PrintStream;
	ldc "n"
	invokevirtual java/io/PrintStream/print(Ljava/lang/String;)V
	goto L17
L261:
	iload 2
	ldc 111
	if_icmpeq L265
	ldc 0
	goto L266
L265:
	ldc 1
L266:
	ifeq L264
	getstatic java/lang/System/out Ljava/io/PrintStream;
	ldc "o"
	invokevirtual java/io/PrintStream/print(Ljava/lang/String;)V
	goto L17
L264:
	iload 2
	ldc 112
	if_icmpeq L268
	ldc 0
	goto L269
L268:
	ldc 1
L269:
	ifeq L267
	getstatic java/lang/System/out Ljava/io/PrintStream;
	ldc "p"
	invokevirtual java/io/PrintStream/print(Ljava/lang/String;)V
	goto L17
L267:
	iload 2
	ldc 113
	if_icmpeq L271
	ldc 0
	goto L272
L271:
	ldc 1
L272:
	ifeq L270
	getstatic java/lang/System/out Ljava/io/PrintStream;
	ldc "q"
	invokevirtual java/io/PrintStream/print(Ljava/lang/String;)V
	goto L17
L270:
	iload 2
	ldc 114
	if_icmpeq L274
	ldc 0
	goto L275
L274:
	ldc 1
L275:
	ifeq L273
	getstatic java/lang/System/out Ljava/io/PrintStream;
	ldc "r"
	invokevirtual java/io/PrintStream/print(Ljava/lang/String;)V
	goto L17
L273:
	iload 2
	ldc 115
	if_icmpeq L277
	ldc 0
	goto L278
L277:
	ldc 1
L278:
	ifeq L276
	getstatic java/lang/System/out Ljava/io/PrintStream;
	ldc "s"
	invokevirtual java/io/PrintStream/print(Ljava/lang/String;)V
	goto L17
L276:
	iload 2
	ldc 116
	if_icmpeq L280
	ldc 0
	goto L281
L280:
	ldc 1
L281:
	ifeq L279
	getstatic java/lang/System/out Ljava/io/PrintStream;
	ldc "t"
	invokevirtual java/io/PrintStream/print(Ljava/lang/String;)V
	goto L17
L279:
	iload 2
	ldc 117
	if_icmpeq L283
	ldc 0
	goto L284
L283:
	ldc 1
L284:
	ifeq L282
	getstatic java/lang/System/out Ljava/io/PrintStream;
	ldc "u"
	invokevirtual java/io/PrintStream/print(Ljava/lang/String;)V
	goto L17
L282:
	iload 2
	ldc 118
	if_icmpeq L286
	ldc 0
	goto L287
L286:
	ldc 1
L287:
	ifeq L285
	getstatic java/lang/System/out Ljava/io/PrintStream;
	ldc "v"
	invokevirtual java/io/PrintStream/print(Ljava/lang/String;)V
	goto L17
L285:
	iload 2
	ldc 119
	if_icmpeq L289
	ldc 0
	goto L290
L289:
	ldc 1
L290:
	ifeq L288
	getstatic java/lang/System/out Ljava/io/PrintStream;
	ldc "w"
	invokevirtual java/io/PrintStream/print(Ljava/lang/String;)V
	goto L17
L288:
	iload 2
	ldc 120
	if_icmpeq L292
	ldc 0
	goto L293
L292:
	ldc 1
L293:
	ifeq L291
	getstatic java/lang/System/out Ljava/io/PrintStream;
	ldc "x"
	invokevirtual java/io/PrintStream/print(Ljava/lang/String;)V
	goto L17
L291:
	iload 2
	ldc 121
	if_icmpeq L295
	ldc 0
	goto L296
L295:
	ldc 1
L296:
	ifeq L294
	getstatic java/lang/System/out Ljava/io/PrintStream;
	ldc "y"
	invokevirtual java/io/PrintStream/print(Ljava/lang/String;)V
	goto L17
L294:
	iload 2
	ldc 122
	if_icmpeq L298
	ldc 0
	goto L299
L298:
	ldc 1
L299:
	ifeq L297
	getstatic java/lang/System/out Ljava/io/PrintStream;
	ldc "z"
	invokevirtual java/io/PrintStream/print(Ljava/lang/String;)V
	goto L17
L297:
	iload 2
	ldc 123
	if_icmpeq L301
	ldc 0
	goto L302
L301:
	ldc 1
L302:
	ifeq L300
	getstatic java/lang/System/out Ljava/io/PrintStream;
	ldc "{"
	invokevirtual java/io/PrintStream/print(Ljava/lang/String;)V
	goto L17
L300:
	iload 2
	ldc 124
	if_icmpeq L304
	ldc 0
	goto L305
L304:
	ldc 1
L305:
	ifeq L303
	getstatic java/lang/System/out Ljava/io/PrintStream;
	ldc "|"
	invokevirtual java/io/PrintStream/print(Ljava/lang/String;)V
	goto L17
L303:
	iload 2
	ldc 125
	if_icmpeq L307
	ldc 0
	goto L308
L307:
	ldc 1
L308:
	ifeq L306
	getstatic java/lang/System/out Ljava/io/PrintStream;
	ldc "}"
	invokevirtual java/io/PrintStream/print(Ljava/lang/String;)V
	goto L17
L306:
	iload 2
	ldc 126
	if_icmpeq L310
	ldc 0
	goto L311
L310:
	ldc 1
L311:
	ifeq L309
	getstatic java/lang/System/out Ljava/io/PrintStream;
	ldc "~"
	invokevirtual java/io/PrintStream/print(Ljava/lang/String;)V
	goto L17
L309:
L17:
	iload 1
	ldc 1
	iadd
	istore 1
	goto L13
L14:
	return
.end method

.method public static join([I[I)[I
.limit stack 10
.limit locals 7
	aload 0
	invokestatic test38.length([I)I
	istore 3
	aload 1
	invokestatic test38.length([I)I
	istore 4
	iload 3
	iload 4
	iadd
	istore 5
	ldc 0
	istore 6
	iload 5
	ldc 1
	iadd
	newarray int
	astore 2
L5:
	iload 6
	iload 3
	if_icmplt L7
	ldc 0
	goto L8
L7:
	ldc 1
L8:
	ifeq L6
	aload 2
	iload 6
	aload 0
	iload 6
	iaload
	iastore
	iload 6
	ldc 1
	iadd
	istore 6
	goto L5
L6:
L9:
	iload 6
	iload 5
	if_icmplt L11
	ldc 0
	goto L12
L11:
	ldc 1
L12:
	ifeq L10
	aload 2
	iload 6
	aload 1
	iload 6
	iload 3
	isub
	iaload
	iastore
	iload 6
	ldc 1
	iadd
	istore 6
	goto L9
L10:
	aload 2
	iload 6
	ldc 0
	iastore
	aload 2
	areturn
	return
.end method

.method public static length([I)I
.limit stack 4
.limit locals 2
	ldc 0
	istore 1
L1:
	aload 0
	iload 1
	iaload
	ldc 0
	if_icmpne L3
	ldc 0
	goto L4
L3:
	ldc 1
L4:
	ifeq L2
	iload 1
	ldc 1
	iadd
	istore 1
	goto L1
L2:
	iload 1
	ireturn
	return
.end method

Success!
